Workbook

Sheet Summary
B2: INCOME | H2: Start Up Package | I2: 1460357
B3: Account | C3: FY24 | D3: FY25 | E3: FY26 | F3: Total | H3: Received | I3: =F10 -> 1039462.1
B4: 1101935 | C4: ='1101935 FY24'!J7 -> 500000 | D4: ='1101935 FY25'!J7 -> 219462 | E4: 0 | F4: =SUM(C4:E4) -> 719462 | H4: Remaining | I4: =I2-I3 -> 420894.93
B5: 5406011 | C5: ='5406011 FY24'!J7 -> 20000 | D5: 0 | E5: 0 | F5: =SUM(C5:E5) -> 20000
B6: 2176351 | C6: 0 | D6: 0 | E6: 0 | F6: =SUM(C6:E6) -> 0
B7: 2176300 BMEAM | C7: 0 | D7: 0 | E7: 0 | F7: =SUM(C7:E7) -> 0
B8: 2215510 BMEAM | C8: ='2215510 BME AM FY24'!J8 -> 300000.07 | D8: 0 | E8: 0 | F8: =SUM(C8:E8) -> 300000.07
B9: 2176301 BMEAM | C9: 0 | D9: 0 | E9: 0 | F9: =SUM(C9:E9) -> 0
B10: Total | C10: =SUM(C4:C9) -> 820000.07 | D10: =SUM(D4:D9) -> 219462 | E10: =SUM(E4:E9) -> 0 | F10: =SUM(F4:F9) -> 1039462.1
B13: EXPENSES
B14: Account | C14: FY24 | D14: FY25 | E14: FY26 | F14: Total
B15: 1101935 | C15: ='1101935 FY24'!H31 -> 452230.88 | D15: ='1101935 FY25'!H40 -> 153596.44 | E15: ='1101935 FY26'!G14+'1101935 FY26'!I14 -> 40507.04 | F15: =SUM(C15:E15) -> 646334.36
B16: 5406011 | C16: ='5406011 FY24'!H10 -> 20000.18 | D16: 0 | E16: 0 | F16: =SUM(C16:E16) -> 20000.18
B17: 2176351 | C17: 0 | D17: ='2176351 FY25'!H9 -> 3284.87 | E17: ='2176351 FY26'!H8 -> 330.37 | F17: =SUM(C17:E17) -> 3615.24
B18: 2176300 BMEAM | C18: ='2176300 BMEAM FY24'!H8 -> 217.6 | D18: ='2176300 BMEAM FY25'!H21 -> 24071.36 | E18: 0 | F18: =SUM(C18:E18) -> 24288.96
B19: 2215510 BMEAM | C19: ='2215510 BME AM FY24'!H11 -> 300000.07 | D19: 0 | E19: 0 | F19: =SUM(C19:E19) -> 300000.07
B20: 2176301 BMEAM | C20: 0 | D20: 0 | E20: 0 | F20: =SUM(C20:E20) -> 0
B21: Total | C21: =SUM(C15:C20) -> 772448.73 | D21: =SUM(D15:D20) -> 180952.67 | E21: =SUM(E15:E20) -> 40837.41 | F21: =SUM(F15:F20) -> 994238.81
B24: AVAILABLE BALANCE
B25: Account | C25: FY24 | D25: FY25 | E25: FY26 | F25: FY26 ACTUALS
B26: 1101935 | C26: =C4-C15 -> 47769.12 | D26: =D4-D15 -> 65865.56 | E26: =E4-E15 -> -40507.04 | F26: =SUM(C26:E26) -> 73127.64
B27: 5406011 | C27: =C5-C16 -> -0.18 | D27: =D5-D16 -> 0 | E27: =E5-E16 -> 0 | F27: =SUM(C27:E27) -> -0.18
B28: 2176351 | C28: =C6-C17 -> 0 | D28: =D6-D17 -> -3284.87 | E28: =E6-E17 -> -330.37 | F28: =SUM(C28:E28) -> -3615.24
B29: 2176300 BMEAM | C29: =C7-C18 -> -217.6 | D29: =D7-D18 -> -24071.36 | E29: =E7-E18 -> 0 | F29: =SUM(C29:E29) -> -24288.96
B30: 2215510 BMEAM | C30: =C8-C19 -> 0 | D30: =D8-D19 -> 0 | E30: =E8-E19 -> 0 | F30: =SUM(C30:E30) -> 0
B31: 2176301 BMEAM | C31: =C9-C20 -> 0 | D31: =D9-D20 -> 0 | E31: =E9-E20 -> 0 | F31: =SUM(C31:E31) -> 0
B32: Total | C32: =SUM(C26:C31) -> 47551.34 | D32: =SUM(D26:D31) -> 38509.33 | E32: =SUM(E26:E31) -> -40837.41 | F32: =SUM(F26:F31) -> 45223.26

Sheet 1101935 FY24
B2: INCOME AND EXPENSE REPORT | L2: TRANSACTION REPORT | AC2: PAYROLL REPORT
B4: Account Number | C4: Consolidation Object Name | D4: Object Code | E4: Object Code Name | F4: Current Budget | G4: Fiscal Year Actuals | H4: Inception to Date | I4: Open Encumbrances | J4: Balance Available | L4: Object Code | M4: Object Code Name | N4: Transaction Date | O4: Document | P4: Document Number | Q4: Origin | R4: e-Doc Link | S4: Post Date | T4: Reference Document Number | U4: Organization Document Number | V4: Entry | W4: Document Description | X4: Vendor Name | Y4: Current Budget Amount | Z4: Current Month Actuals | AA4: Encumbrance Amount | AC4: Account Number | AD4: Sub Account Number | AE4: Employee Name | AF4: Position Number | AG4: Object Code | AH4: Object Code Name | AI4: Pay Period Earn Date | AJ4: Document Type Code | AK4: Job FTE | AL4: Hours Worked | AM4: Expenditure Amount
B5: 1101935 | C5: OTHER REVENUE | D5: 0899 | E5: Net Revenues - FSO Only | F5: 0 | G5: 0 | H5: 0 | I5: 0 | J5: 0 | L5: 0932 | M5: Budget Adjustment Income Transfer | N5: 45448 | O5: TF | P5: B212966 | Q5: BO | R5: Link Not Available | S5: 45448 | T5: - | U5: 2024060450 | V5: FY24 BME NEI CANCER ENGR ALLOCATION_ALE | W5: - | X5: - | Y5: 0 | Z5: -500000 | AA5: 0 | AC5: 1101935 | AD5: - | AE5: McGhee,Alexander | AF5: 1867411 | AG5: 1212 | AH5: Supp Com Regular App/Fac (ere 4) | AI5: 45438 | AJ5: LLPR | AK5: 0.025 | AL5: 40 | AM5: 3216.4
C6: TRANSFER OF FUNDS | D6: 0932 | E6: Budget Adjustment Income Transfer | F6: 0 | G6: -500000 | H6: -500000 | I6: 0 | J6: 500000 | L6: 0932 Total | Y6: 0 | Z6: -500000 | AA6: 0 | AI6: 45452 | AJ6: LLPR | AK6: 0.025 | AL6: 32 | AM6: 2573.12
C7: INCOME Total | F7: 0 | G7: -500000 | H7: -500000 | I7: 0 | J7: 500000 | L7: 1000 | M7: Personal Services-Budget | N7: 45446 | O7: BTR | P7: B212966 | Q7: BO | R7: Link Not Available | S7: 45448 | T7: - | U7: 2024060450 | V7: FY24 BME NEI CANCER ENGR ALLOCATION_ALE | W7: - | X7: - | Y7: 500000 | Z7: 0 | AA7: 0 | AI7: 45466 | AJ7: LLPR | AK7: 0.025 | AL7: 72 | AM7: 5789.52
C8: PERSONAL SERVICES | D8: 1000 | E8: Personal Services-Budget | F8: 500000 | G8: 0 | H8: 0 | I8: 0 | J8: 500000 | L8: 1000 Total | Y8: 500000 | Z8: 0 | AA8: 0 | AI8: 45480 | AJ8: LLPR | AK8: 0.025 | AL8: 40 | AM8: 3216.4
D9: 1212 | E9: Supp Com Regular App/Fac (ere 4) | F9: 0 | G9: 14795.44 | H9: 14795.44 | I9: 0 | J9: -14795.44 | L9: 1212 | M9: Supp Com Regular App/Fac (ere 4) | N9: 45434 | O9: LLPE | P9: 20240522200001 | Q9: UE | R9: Link Not Available | S9: 45434 | T9: - | U9: - | V9: PAYROLL ENCUMBRANCES | W9: - | X9: - | Y9: 0 | Z9: 0 | AA9: 563 | AG9: 1212 Total | AL9: 184 | AM9: 14795.44
D10: 2121 | E10: Employee Full-Benefit ERE | F10: 0 | G10: 4734.55 | H10: 4734.55 | I10: 0 | J10: -4734.55 | N10: 45441 | O10: LLPE | P10: 20240529200001 | Q10: MF | R10: Link Not Available | S10: 45441 | T10: - | U10: - | V10: PAYROLL ENCUMBRANCES | W10: - | X10: - | Y10: 0 | Z10: 0 | AA10: -161 | AG10: 2121 | AH10: Employee Full-Benefit ERE | AI10: 45438 | AJ10: LLPR | AK10: 0.025 | AL10: 0 | AM10: 1029.25
C11: GENERAL EXPENSES | D11: 3590 | E11: R/M Services-Office Furniture & Equipment | F11: 0 | G11: 196.08 | H11: 196.08 | I11: 0 | J11: -196.08 | O11: LLPR | P11: 20240531100001 | Q11: UE | R11: Link Not Available | S11: 45441 | T11: - | U11: 11 | V11: NORMAL PAYROLL ACTIVITY | W11: - | X11: - | Y11: 0 | Z11: 3216.4 | AA11: 0 | AI11: 45452 | AJ11: LLPR | AK11: 0.025 | AL11: 0 | AM11: 823.4
D12: 3780 | E12: R/M Services-Other | F12: 0 | G12: 81.56 | H12: 81.56 | I12: 0 | J12: -81.56 | N12: 45455 | O12: LLPE | P12: 20240612200001 | Q12: MF | R12: Link Not Available | S12: 45455 | T12: - | U12: - | V12: PAYROLL ENCUMBRANCES | W12: - | X12: - | Y12: 0 | Z12: 0 | AA12: -161 | AI12: 45466 | AJ12: LLPR | AK12: 0.025 | AL12: 0 | AM12: 1852.65
D13: 3880 | E13: Shipping & Handling | F13: 0 | G13: 40 | H13: 40 | I13: 0 | J13: -40 | N13: 45469 | O13: LLPE | P13: 20240626200001 | Q13: MF | R13: Link Not Available | S13: 45469 | T13: - | U13: - | V13: PAYROLL ENCUMBRANCES | W13: - | X13: - | Y13: 0 | Z13: 0 | AA13: -161 | AI13: 45480 | AJ13: LLPR | AK13: 0.025 | AL13: 0 | AM13: 1029.25
D14: 5230 | E14: Office Supplies | F14: 0 | G14: 1143.34 | H14: 1143.34 | I14: 0 | J14: -1143.34 | O14: LLPR | P14: 20240628100001 | Q14: UE | R14: Link Not Available | S14: 45469 | T14: - | U14: 12 | V14: NORMAL PAYROLL ACTIVITY | W14: - | X14: - | Y14: 0 | Z14: 8362.64 | AA14: 0 | AG14: 2121 Total | AL14: 0 | AM14: 4734.55
D15: 5260 | E15: R/M Supplies - Shop | F15: 0 | G15: 441.8 | H15: 441.8 | I15: 0 | J15: -441.8 | N15: 45483 | O15: LLPR | P15: 20240712100001 | Q15: UE | R15: Link Not Available | S15: 45483 | T15: - | U15: 12 | V15: NORMAL PAYROLL ACTIVITY | W15: - | X15: - | Y15: 0 | Z15: 3216.4 | AA15: 0 | AD15: - Total | AL15: 184 | AM15: 19529.99
D16: 5270 | E16: R/M Supplies - Other | F16: 0 | G16: 1757.21 | H16: 1757.21 | I16: 0 | J16: -1757.21 | N16: 45485 | O16: LLPE | P16: 20240630200000 | Q16: MF | R16: Link Not Available | S16: 45485 | T16: - | U16: - | V16: PAYROLL ENCUMBRANCES | W16: - | X16: - | Y16: 0 | Z16: 0 | AA16: -80 | AC16: 1101935 Total | AL16: 184 | AM16: 19529.99
D17: 5290 | E17: Research Supplies/Medical - Laboratory | F17: 0 | G17: 11720.26 | H17: 11720.26 | I17: 0 | J17: -11720.26 | L17: 1212 Total | Y17: 0 | Z17: 14795.44 | AA17: 0 | AC17: Grand Total | AL17: 184 | AM17: 19529.99
D18: 5490 | E18: Operating Supplies - Other | F18: 0 | G18: 11705.31 | H18: 11705.31 | I18: 0 | J18: -11705.31 | L18: 2121 | M18: Employee Full-Benefit ERE | N18: 45434 | O18: LLPE | P18: 20240522200001 | Q18: UE | R18: Link Not Available | S18: 45434 | T18: - | U18: - | V18: PAYROLL ENCUMBRANCES | W18: - | X18: - | Y18: 0 | Z18: 0 | AA18: 180.16
D19: 5520 | E19: Conference Registration Fees | F19: 0 | G19: 1400 | H19: 1400 | I19: 0 | J19: -1400 | N19: 45441 | O19: LLPE | P19: 20240529200001 | Q19: MF | R19: Link Not Available | S19: 45441 | T19: - | U19: - | V19: PAYROLL ENCUMBRANCES | W19: - | X19: - | Y19: 0 | Z19: 0 | AA19: -51.52
D20: 5535 | E20: Purchasing Transaction Fees | F20: 0 | G20: 54.75 | H20: 54.75 | I20: 0 | J20: -54.75 | O20: LLPR | P20: 20240531100001 | Q20: UE | R20: Link Not Available | S20: 45441 | T20: - | U20: 11 | V20: NORMAL PAYROLL ACTIVITY | W20: - | X20: - | Y20: 0 | Z20: 1029.25 | AA20: 0
D21: 5560 | E21: Freight In/Out - (Noncapital related) | F21: 0 | G21: 1046.41 | H21: 1046.41 | I21: 0 | J21: -1046.41 | N21: 45455 | O21: LLPE | P21: 20240612200001 | Q21: MF | R21: Link Not Available | S21: 45455 | T21: - | U21: - | V21: PAYROLL ENCUMBRANCES | W21: - | X21: - | Y21: 0 | Z21: 0 | AA21: -51.52
D22: 5760 | E22: Noncapitalized Equipment - EDP | F22: 0 | G22: 5550.42 | H22: 5550.42 | I22: 0 | J22: -5550.42 | N22: 45469 | O22: LLPE | P22: 20240626200001 | Q22: MF | R22: Link Not Available | S22: 45469 | T22: - | U22: - | V22: PAYROLL ENCUMBRANCES | W22: - | X22: - | Y22: 0 | Z22: 0 | AA22: -51.52
D23: 5770 | E23: Noncapitalized Equipment - Other | F23: 0 | G23: 49076.25 | H23: 49076.25 | I23: 483.2 | J23: -49559.45 | O23: LLPR | P23: 20240628100001 | Q23: UE | R23: Link Not Available | S23: 45469 | T23: - | U23: 12 | V23: NORMAL PAYROLL ACTIVITY | W23: - | X23: - | Y23: 0 | Z23: 2676.05 | AA23: 0
D24: 5775 | E24: Noncapitalized Furnishings | F24: 0 | G24: 2457.94 | H24: 2457.94 | I24: 0 | J24: -2457.94 | N24: 45483 | O24: LLPR | P24: 20240712100001 | Q24: UE | R24: Link Not Available | S24: 45483 | T24: - | U24: 12 | V24: NORMAL PAYROLL ACTIVITY | W24: - | X24: - | Y24: 0 | Z24: 1029.25 | AA24: 0
D25: 5780 | E25: Miscellaneous - Other Operating | F25: 0 | G25: 788.57 | H25: 788.57 | I25: 0 | J25: -788.57 | N25: 45485 | O25: LLPE | P25: 20240630200000 | Q25: MF | R25: Link Not Available | S25: 45485 | T25: - | U25: - | V25: PAYROLL ENCUMBRANCES | W25: - | X25: - | Y25: 0 | Z25: 0 | AA25: -25.6
D26: 5899 | E26: Net Expenses - FSO Only | F26: 0 | G26: 0 | H26: 0 | I26: 0 | J26: 0 | L26: 2121 Total | Y26: 0 | Z26: 4734.55 | AA26: -2.8421709e-14
C27: TRAVEL | D27: 6240 | E27: TRAVEL-OUT STATE | F27: 0 | G27: 142.27 | H27: 142.27 | I27: 0 | J27: -142.27 | L27: 3590 | M27: R/M Services-Office Furniture & Equipmen | N27: 45365 | O27: PCDO | P27: 27221074 | Q27: 01 | R27: View Document | S27: 45365 | T27: - | U27: - | V27: Paint, Pure Tung Oil, Orange Peel Oil | W27: Procurement Card - 5745 / MCGHEE, ALEXANDER / 3737 / AMZN Mktp US RN6LU60V2 / $196.08 | X27: - | Y27: 0 | Z27: 196.08 | AA27: 0
D28: 6241 | E28: TRAVEL-OUT OF STATE AIRLINES | F28: 0 | G28: 1399.15 | H28: 1399.15 | I28: 0 | J28: -1399.15 | L28: 3590 Total | Y28: 0 | Z28: 196.08 | AA28: 0
D29: 6242 | E29: TRAVEL-OUT STATE HOTEL | F29: 0 | G29: 847.86 | H29: 847.86 | I29: 0 | J29: -847.86 | L29: 3780 | M29: R/M Services-Other | N29: 45462 | O29: PCDO | P29: 28040101 | Q29: 01 | R29: View Document | S29: 45463 | T29: - | U29: - | V29: Supplies | W29: Procurement Card - 5745 / MCGHEE, ALEXANDER / 44619 / THE HOME DEPOT #0486 / $81.56 | X29: - | Y29: 0 | Z29: 81.56 | AA29: 0
C30: CAPITAL | D30: 7690 | E30: Scientific Equipment | F30: 0 | G30: 342851.71 | H30: 342851.71 | I30: 13409.23 | J30: -356260.94 | L30: 3780 Total | Y30: 0 | Z30: 81.56 | AA30: 0
C31: EXPENSES Total | F31: 500000 | G31: 452230.88 | H31: 452230.88 | I31: 13892.43 | J31: 33876.69 | L31: 3880 | M31: Shipping & Handling | N31: 45342 | O31: PCDO | P31: 26987701 | Q31: 01 | R31: View Document | S31: 45342 | T31: - | U31: - | V31: Office and lab Reno Supplies SandH | W31: Procurement Card - 3322 / CANCER CENTER, ARIZONA / 4382589607001 / AMZN MKTP US / $577.92 | X31: - | Y31: 0 | Z31: 40 | AA31: 0
B32: Grand Total | F32: 500000 | G32: -47769.12 | H32: -47769.12 | I32: 13892.43 | J32: 533876.69 | L32: 3880 Total | Y32: 0 | Z32: 40 | AA32: 0
L33: 5230 | M33: Office Supplies | N33: 45412 | O33: PCDO | P33: 27640100 | Q33: 01 | R33: View Document | S33: 45412 | T33: - | U33: - | V33: office supplies- storage bins | W33: Procurement Card - 5745 / MCGHEE, ALEXANDER / 23105 / AMZN Mktp US QK45I4KX3 / $1065.10 | X33: - | Y33: 0 | Z33: 1065.1 | AA33: 0
N34: 45414 | O34: PCDO | P34: 27596330 | Q34: 01 | R34: View Document | S34: 45414 | T34: - | U34: - | V34: office supplies- storage boxes | W34: Procurement Card - 5745 / MCGHEE, ALEXANDER / 20135 / Amazon.com AG4TX44I3 / $78.24 | X34: - | Y34: 0 | Z34: 78.24 | AA34: 0
L35: 5230 Total | Y35: 0 | Z35: 1143.34 | AA35: 0
L36: 5260 | M36: R/M Supplies - Shop | N36: 45365 | O36: PCDO | P36: 27155406 | Q36: 01 | R36: View Document | S36: 45365 | T36: - | U36: - | V36: Amazon total | W36: Procurement Card - 5745 / MCGHEE, ALEXANDER / 2567 / AMZN Mktp US RW1NM8SU1 / $441.80 | X36: - | Y36: 0 | Z36: 441.8 | AA36: 0
L37: 5260 Total | Y37: 0 | Z37: 441.8 | AA37: 0
L38: 5270 | M38: R/M Supplies - Other | N38: 45365 | O38: PCDO | P38: 27249962 | Q38: 01 | R38: View Document | S38: 45365 | T38: - | U38: - | V38: Supplies for renovation | W38: Procurement Card - 5745 / MCGHEE, ALEXANDER / 4608 / THE HOME DEPOT #0414 / $294.09 | X38: - | Y38: 0 | Z38: 294.09 | AA38: 0
P39: 27249963 | Q39: 01 | R39: View Document | S39: 45365 | T39: - | U39: - | V39: Supplies for renovation | W39: Procurement Card - 5745 / MCGHEE, ALEXANDER / 4552 / AMZN Mktp US RN2AB1I82 / $522.01 | X39: - | Y39: 0 | Z39: 522.01 | AA39: 0
N40: 45373 | O40: PCDO | P40: 27287014 | Q40: 01 | R40: View Document | S40: 45373 | T40: - | U40: - | V40: 5745 / MCGHEE, ALEXANDER | W40: Procurement Card - 5745 / MCGHEE, ALEXANDER / 5650 / AMZN Mktp US / $-55.01 | X40: - | Y40: 0 | Z40: -55.01 | AA40: 0
N41: 45390 | O41: PCDO | P41: 27380726 | Q41: 01 | R41: View Document | S41: 45390 | T41: - | U41: - | V41: Supplies for lab remodel | W41: Procurement Card - 5745 / MCGHEE, ALEXANDER / 8974 / THE HOME DEPOT #0414 / $702.37 | X41: - | Y41: 0 | Z41: 702.37 | AA41: 0
P42: 27391196 | Q42: 01 | R42: View Document | S42: 45390 | T42: - | U42: - | V42: Supplies for lab remodel | W42: Procurement Card - 5745 / MCGHEE, ALEXANDER / 9730 / THE HOME DEPOT #0486 / $217.77 | X42: - | Y42: 0 | Z42: 217.77 | AA42: 0
N43: 45418 | O43: PCDO | P43: 27596331 | Q43: 01 | R43: View Document | S43: 45418 | T43: - | U43: - | V43: Isopropyl Alcohol | W43: Procurement Card - 5745 / MCGHEE, ALEXANDER / 20459 / AMZN Mktp US 9C51L1J13 / $75.98 | X43: - | Y43: 0 | Z43: 75.98 | AA43: 0
L44: 5270 Total | Y44: 0 | Z44: 1757.21 | AA44: 0
L45: 5290 | M45: Research Supplies/Medical - Laboratory | N45: 45349 | O45: PO | P45: 27100496 | Q45: 01 | R45: View Document | S45: 45349 | T45: 745248 | U45: - | V45: SURPLUS SOLUTIONS LLC | W45: Purchase Order - Alexander McGhee - Surplus Solutions LLC | X45: SURPLUS SOLUTIONS LLC | Y45: 0 | Z45: 0 | AA45: 300
N46: 45351 | O46: PREQ | P46: 27131938 | Q46: 01 | R46: View Document | S46: 45351 | T46: 745248 | U46: - | V46: SURPLUS SOLUTIONS LLC | W46: PO: 745248 Vendor: SURPLUS SOLUTIONS LLC Amount: 21179.00 | X46: SURPLUS SOLUTIONS LLC | Y46: 0 | Z46: 300 | AA46: -300
N47: 45373 | O47: PCDO | P47: 27249964 | Q47: 01 | R47: View Document | S47: 45373 | T47: - | U47: - | V47: Materials to refinish table tops in lab | W47: Procurement Card - 5745 / MCGHEE, ALEXANDER / 4686 / FLINN SCIENTIFIC INC / $245.42 | X47: - | Y47: 0 | Z47: 245.42 | AA47: 0
N48: 45392 | O48: PCDO | P48: 27380724 | Q48: 01 | R48: View Document | S48: 45392 | T48: - | U48: - | V48: Lab supplies (tax added to this amount) | W48: Procurement Card - 5745 / MCGHEE, ALEXANDER / 9154 / AMZN Mktp US RH8H41D22 / $400.82 | X48: - | Y48: 0 | Z48: 300.87 | AA48: 0
P49: 27380725 | Q49: 01 | R49: View Document | S49: 45392 | T49: - | U49: - | V49: Lab supplies (tax added to this amount) | W49: Procurement Card - 5745 / MCGHEE, ALEXANDER / 8594 / AMZN Mktp US RA4UM9CP2 / $2573.06 | X49: - | Y49: 0 | Z49: 1344.99 | AA49: 0
N50: 45412 | O50: PCDO | P50: 27611298 | Q50: 01 | R50: View Document | S50: 45412 | T50: - | U50: - | V50: 5745 / MCGHEE, ALEXANDER | W50: Procurement Card - 5745 / MCGHEE, ALEXANDER / 22023 / DRILLSANDCUTTERS.COM / $42.89 | X50: - | Y50: 0 | Z50: 34.9 | AA50: 0
V51: Use Tax 5.600% on 34.90 | W51: Procurement Card - 5745 / MCGHEE, ALEXANDER / 22023 / DRILLSANDCUTTERS.COM / $42.89 | X51: - | Y51: 0 | Z51: 1.95 | AA51: 0
P52: 27640099 | Q52: 01 | R52: View Document | S52: 45412 | T52: - | U52: - | V52: 5745 / MCGHEE, ALEXANDER | W52: Procurement Card - 5745 / MCGHEE, ALEXANDER / 22682 / MCMASTER-CARR / $253.36 | X52: - | Y52: 0 | Z52: 243.38 | AA52: 0
N53: 45425 | O53: PCDO | P53: 27742893 | Q53: 01 | R53: View Document | S53: 45425 | T53: - | U53: - | V53: Syringes | W53: Procurement Card - 5745 / MCGHEE, ALEXANDER / 28899 / HAMILTON COMPANY / $1904.17 | X53: - | Y53: 0 | Z53: 1887.9 | AA53: 0
N54: 45427 | O54: PCDO | P54: 27831683 | Q54: 01 | R54: View Document | S54: 45427 | T54: - | U54: - | V54: Supplies for McGhee Lab (syringes) | W54: Procurement Card - 5745 / MCGHEE, ALEXANDER / 34019 / HAMILTON COMPANY / $149.27 | X54: - | Y54: 0 | Z54: 134.85 | AA54: 0
O55: PO | P55: 27829653 | Q55: 01 | R55: View Document | S55: 45427 | T55: 756761 | U55: - | V55: UNCHAINED LABS LLC | W55: Purchase Order - Alexander Mcghee - Dolomite | X55: UNCHAINED LABS LLC | Y55: 0 | Z55: 0 | AA55: 3590
N56: 45436 | O56: PCDO | P56: 27900007 | Q56: 01 | R56: View Document | S56: 45436 | T56: - | U56: - | V56: Supplies for Mcghee Lab | W56: Procurement Card - 5745 / MCGHEE, ALEXANDER / 37796 / AMZN Mktp US 0Q3MH8YA3 / $303.44 | X56: - | Y56: 0 | Z56: 303.44 | AA56: 0
N57: 45462 | O57: PREQ | P57: 28192433 | Q57: 01 | R57: View Document | S57: 45463 | T57: 756761 | U57: - | V57: UNCHAINED LABS LLC | W57: PO: 756761 Vendor: UNCHAINED LABS LLC Amount: 3622.56 | X57: UNCHAINED LABS LLC | Y57: 0 | Z57: 3622.56 | AA57: -3590
N58: 45466 | O58: PCDO | P58: 28053244 | Q58: 01 | R58: View Document | S58: 45467 | T58: - | U58: - | V58: 48 well plates | W58: Procurement Card - Auto Approve 06/23/2024 12:51 AM / 45149 / AURITA BIOTECH / $3300.00 | X58: - | Y58: 0 | Z58: 3300 | AA58: 0
L59: 5290 Total | Y59: 0 | Z59: 11720.26 | AA59: 0
L60: 5490 | M60: Operating Supplies - Other | N60: 45342 | O60: PCDO | P60: 26912771 | Q60: 01 | R60: View Document | S60: 45342 | T60: - | U60: - | V60: Butcher block counter tops | W60: Procurement Card - 0522 / PALSSON, ERIKA / 4375217472001 / AMAZON.COM*R275J2BJ2 / $1430.94 | X60: - | Y60: 0 | Z60: 1430.94 | AA60: 0
P61: 26912772 | Q61: 01 | R61: View Document | S61: 45342 | T61: - | U61: - | V61: Metal table legs for office and lab reno | W61: Procurement Card - 0522 / PALSSON, ERIKA / 4375217473001 / AMZN MKTP US / $208.68 | X61: - | Y61: 0 | Z61: 208.68 | AA61: 0
P62: 26912773 | Q62: 01 | R62: View Document | S62: 45342 | T62: - | U62: - | V62: Supplies to reno lab and office | W62: Procurement Card - 0522 / PALSSON, ERIKA / 4375217474001 / AMZN MKTP US / $1432.40 | X62: - | Y62: 0 | Z62: 1432.4 | AA62: 0
P63: 26912774 | Q63: 01 | R63: View Document | S63: 45342 | T63: - | U63: - | V63: Lab and office renovation supplies | W63: Procurement Card - 0522 / PALSSON, ERIKA / 4375217470001 / AMZN MKTP US / $958.74 | X63: - | Y63: 0 | Z63: 958.74 | AA63: 0
P64: 26912775 | Q64: 01 | R64: View Document | S64: 45342 | T64: - | U64: - | V64: Tyvek Coverall | W64: Procurement Card - 0522 / PALSSON, ERIKA / 4375217471001 / AMZN MKTP US / $24.78 | X64: - | Y64: 0 | Z64: 24.78 | AA64: 0
P65: 26987700 | Q65: 01 | R65: View Document | S65: 45342 | T65: - | U65: - | V65: Office and lab Reno supplies | W65: Procurement Card - 3322 / CANCER CENTER, ARIZONA / 4382589606001 / AMAZON.COM*RI2LA33V0 / $3759.70 | X65: - | Y65: 0 | Z65: 3759.7 | AA65: 0
P66: 26987701 | Q66: 01 | R66: View Document | S66: 45342 | T66: - | U66: - | V66: Office and lab Reno supplies | W66: Procurement Card - 3322 / CANCER CENTER, ARIZONA / 4382589607001 / AMZN MKTP US / $577.92 | X66: - | Y66: 0 | Z66: 537.92 | AA66: 0
N67: 45344 | O67: PCDO | P67: 26952735 | Q67: 01 | R67: View Document | S67: 45344 | T67: - | U67: - | V67: Wood Butcher Block Countertop | W67: Procurement Card - 3322 / CANCER CENTER, ARIZONA / 4379884221001 / AMAZON.COM*RB0RJ50V2 / $476.98 | X67: - | Y67: 0 | Z67: 476.98 | AA67: 0
P68: 26954123 | Q68: 01 | R68: View Document | S68: 45344 | T68: - | U68: - | V68: Floating Shelf Bracket (x10) | W68: Procurement Card - 3322 / CANCER CENTER, ARIZONA / 4381272298001 / AMZN MKTP US / $1597.90 | X68: - | Y68: 0 | Z68: 1597.9 | AA68: 0
P69: 26954124 | Q69: 01 | R69: View Document | S69: 45344 | T69: - | U69: - | V69: Outlet Surge Protector Power Strip (x2) | W69: Procurement Card - 3322 / CANCER CENTER, ARIZONA / 4381272297001 / AMZN MKTP US / $125.18 | X69: - | Y69: 0 | Z69: 125.18 | AA69: 0
N70: 45350 | O70: PCDO | P70: 27025573 | Q70: 01 | R70: View Document | S70: 45350 | T70: - | U70: - | V70: 5 lab stool chairs @ 105.99 each | W70: Procurement Card - 0522 / PALSSON, ERIKA / 4388470110001 / AMZN MKTP US / $576.05 | X70: - | Y70: 0 | Z70: 576.05 | AA70: 0
P71: 27053057 | Q71: 01 | R71: View Document | S71: 45350 | T71: - | U71: - | V71: lab and office renovation | W71: Procurement Card - 0522 / PALSSON, ERIKA / 4390077399001 / AMZN MKTP US / $576.04 | X71: - | Y71: 0 | Z71: 576.04 | AA71: 0
L72: 5490 Total | Y72: 0 | Z72: 11705.31 | AA72: 0
L73: 5520 | M73: Conference Registration Fees | N73: 45421 | O73: DVCA | P73: 27617327 | Q73: 01 | R73: View Document | S73: 45421 | T73: - | U73: T41561 | V73: Event Registration &amp; Event Dinner | W73: Disbursement Voucher T - Travel Expense - Alexander Mcghee - Florida [E:N] | X73: - | Y73: 0 | Z73: 350 | AA73: 0
N74: 45425 | O74: PCDO | P74: 27742892 | Q74: 01 | R74: View Document | S74: 45425 | T74: - | U74: - | V74: Non member registration | W74: Procurement Card - 5745 / MCGHEE, ALEXANDER / 28951 / SOC FOR EXPER MECH / $1050.00 | X74: - | Y74: 0 | Z74: 1050 | AA74: 0
L75: 5520 Total | Y75: 0 | Z75: 1400 | AA75: 0
L76: 5535 | M76: Purchasing Transaction Fees | N76: 45373 | O76: PCDO | P76: 27185986 | Q76: 01 | R76: View Document | S76: 45373 | T76: - | U76: - | V76: Processing | W76: Procurement Card - 5745 / MCGHEE, ALEXANDER / 2942 / CK SURPLUS SOLUTIONS / $1879.75 | X76: - | Y76: 0 | Z76: 54.75 | AA76: 0
L77: 5535 Total | Y77: 0 | Z77: 54.75 | AA77: 0
L78: 5560 | M78: Freight In/Out - (Noncapital related) | N78: 45328 | O78: PO | P78: 26787321 | Q78: 01 | R78: View Document | S78: 45328 | T78: 740334 | U78: - | V78: FORMLABS | W78: Purchase Order - Alexander McGhee - FormLabs | X78: FORMLABS | Y78: 0 | Z78: 0 | AA78: 92.3
N79: 45337 | O79: PREQ | P79: 27001315 | Q79: 01 | R79: View Document | S79: 45337 | T79: 740334 | U79: - | V79: FORMLABS | W79: PO: 740334 Vendor: FORMLABS Amount: 9460.17 | X79: FORMLABS | Y79: 0 | Z79: 97.75 | AA79: -92.3
N80: 45412 | O80: PCDO | P80: 27611298 | Q80: 01 | R80: View Document | S80: 45412 | T80: - | U80: - | V80: 5745 / MCGHEE, ALEXANDER | W80: Procurement Card - 5745 / MCGHEE, ALEXANDER / 22023 / DRILLSANDCUTTERS.COM / $42.89 | X80: - | Y80: 0 | Z80: 7.99 | AA80: 0
P81: 27640099 | Q81: 01 | R81: View Document | S81: 45412 | T81: - | U81: - | V81: 5745 / MCGHEE, ALEXANDER | W81: Procurement Card - 5745 / MCGHEE, ALEXANDER / 22682 / MCMASTER-CARR / $253.36 | X81: - | Y81: 0 | Z81: 9.98 | AA81: 0
O82: PO | P82: 27618811 | Q82: 01 | R82: View Document | S82: 45412 | T82: 753373 | U82: - | V82: FISHER SCIENTIFIC COMPANY LLC | W82: Purchase Order - Alexander McGhee - Fisher Scientific | X82: FISHER SCIENTIFIC COMPANY LLC | Y82: 0 | Z82: 0 | AA82: 900
N83: 45425 | O83: PCDO | P83: 27742893 | Q83: 01 | R83: View Document | S83: 45425 | T83: - | U83: - | V83: Fright costs | W83: Procurement Card - 5745 / MCGHEE, ALEXANDER / 28899 / HAMILTON COMPANY / $1904.17 | X83: - | Y83: 0 | Z83: 16.27 | AA83: 0
N84: 45427 | O84: PCDO | P84: 27831683 | Q84: 01 | R84: View Document | S84: 45427 | T84: - | U84: - | V84: Shipping cost | W84: Procurement Card - 5745 / MCGHEE, ALEXANDER / 34019 / HAMILTON COMPANY / $149.27 | X84: - | Y84: 0 | Z84: 14.42 | AA84: 0
N85: 45457 | O85: PRNC | P85: 28152614 | Q85: 01 | R85: View Document | S85: 45457 | T85: 753373 | U85: - | V85: FISHER SCIENTIFIC COMPANY LLC | W85: PO: 753373 Vendor: FISHER SCIENTIFIC COMPANY LLC Account: UA 1101935 Amount: 16928.75 Pay Date: 07/02/2024 | X85: FISHER SCIENTIFIC COMPANY LLC | Y85: 0 | Z85: 900 | AA85: -900
L86: 5560 Total | Y86: 0 | Z86: 1046.41 | AA86: 4.2632564e-14
L87: 5760 | M87: Noncapitalized Equipment - EDP | N87: 45343 | O87: DVCA | P87: 26968150 | Q87: 01 | R87: View Document | S87: 45343 | T87: - | U87: - | V87: Apple | W87: Disbursement Voucher E - Expense Reimbursement - Alexander McGhee - Apple [E:N] | X87: - | Y87: 0 | Z87: 5540.43 | AA87: 0
N88: 45392 | O88: PCDO | P88: 27380725 | Q88: 01 | R88: View Document | S88: 45392 | T88: - | U88: - | V88: Wifi adapter | W88: Procurement Card - 5745 / MCGHEE, ALEXANDER / 8594 / AMZN Mktp US RA4UM9CP2 / $2573.06 | X88: - | Y88: 0 | Z88: 9.99 | AA88: 0
L89: 5760 Total | Y89: 0 | Z89: 5550.42 | AA89: 0
L90: 5770 | M90: Noncapitalized Equipment - Other | N90: 45328 | O90: PO | P90: 26787321 | Q90: 01 | R90: View Document | S90: 45328 | T90: 740334 | U90: - | V90: FORMLABS | W90: Purchase Order - Alexander McGhee - FormLabs | X90: FORMLABS | Y90: 0 | Z90: 0 | AA90: 9510.33
N91: 45337 | O91: PREQ | P91: 27001315 | Q91: 01 | R91: View Document | S91: 45337 | T91: 740334 | U91: - | V91: FORMLABS | W91: PO: 740334 Vendor: FORMLABS Amount: 9460.17 | X91: FORMLABS | Y91: 0 | Z91: 9362.42 | AA91: -9141.79
N92: 45383 | O92: PO | P92: 27400501 | Q92: 01 | R92: View Document | S92: 45383 | T92: 749977 | U92: - | V92: DINGS MOTION USA LLC | W92: Purchase Order - Alexander McGhee - Dings Motion | X92: DINGS MOTION USA LLC | Y92: 0 | Z92: 0 | AA92: 4272.16
N93: 45392 | O93: PCDO | P93: 27380724 | Q93: 01 | R93: View Document | S93: 45392 | T93: - | U93: - | V93: OXO Coffee Grinder | W93: Procurement Card - 5745 / MCGHEE, ALEXANDER / 9154 / AMZN Mktp US RH8H41D22 / $400.82 | X93: - | Y93: 0 | Z93: 99.95 | AA93: 0
P94: 27380725 | Q94: 01 | R94: View Document | S94: 45392 | T94: - | U94: - | V94: Siglent tech | W94: Procurement Card - 5745 / MCGHEE, ALEXANDER / 8594 / AMZN Mktp US RA4UM9CP2 / $2573.06 | X94: - | Y94: 0 | Z94: 1218.08 | AA94: 0
N95: 45412 | O95: PO | P95: 27618811 | Q95: 01 | R95: View Document | S95: 45412 | T95: 753373 | U95: - | V95: FISHER SCIENTIFIC COMPANY LLC | W95: Purchase Order - Alexander McGhee - Fisher Scientific | X95: FISHER SCIENTIFIC COMPANY LLC | Y95: 0 | Z95: 0 | AA95: 33895.49
N96: 45436 | O96: PRNC | P96: 27932996 | Q96: 01 | R96: View Document | S96: 45436 | T96: 753373 | U96: - | V96: FISHER SCIENTIFIC COMPANY LLC | W96: PO: 753373 Vendor: FISHER SCIENTIFIC COMPANY LLC Account: UA 1101935 Amount: 3284.08 Pay Date: 06/04/2024 | X96: FISHER SCIENTIFIC COMPANY LLC | Y96: 0 | Z96: 3284.08 | AA96: -3284.08
P97: 27933695 | Q97: 01 | R97: View Document | S97: 45436 | T97: 753373 | U97: - | V97: FISHER SCIENTIFIC COMPANY LLC | W97: PO: 753373 Vendor: FISHER SCIENTIFIC COMPANY LLC Account: UA 1101935 Amount: 11670.99 Pay Date: 06/03/2024 | X97: FISHER SCIENTIFIC COMPANY LLC | Y97: 0 | Z97: 11670.99 | AA97: -11670.99
P98: 27936155 | Q98: 01 | R98: View Document | S98: 45436 | T98: 753373 | U98: - | V98: FISHER SCIENTIFIC COMPANY LLC | W98: PO: 753373 Vendor: FISHER SCIENTIFIC COMPANY LLC Account: UA 1101935 Amount: 902.24 Pay Date: 06/05/2024 | X98: FISHER SCIENTIFIC COMPANY LLC | Y98: 0 | Z98: 902.24 | AA98: -902.24
N99: 45437 | O99: PRNC | P99: 27939663 | Q99: 01 | R99: View Document | S99: 45440 | T99: 753373 | U99: - | V99: FISHER SCIENTIFIC COMPANY LLC | W99: PO: 753373 Vendor: FISHER SCIENTIFIC COMPANY LLC Account: UA 1101935 Amount: 10319.73 Pay Date: 06/08/2024 | X99: FISHER SCIENTIFIC COMPANY LLC | Y99: 0 | Z99: 596.88 | AA99: -596.88
P100: 27940050 | Q100: 01 | R100: View Document | S100: 45440 | T100: 753373 | U100: - | V100: FISHER SCIENTIFIC COMPANY LLC | W100: PO: 753373 Vendor: FISHER SCIENTIFIC COMPANY LLC Account: UA 1101935 Amount: 2522.37 Pay Date: 06/09/2024 | X100: FISHER SCIENTIFIC COMPANY LLC | Y100: 0 | Z100: 2522.37 | AA100: -2522.37
N101: 45441 | O101: PREQ | P101: 27951933 | Q101: 01 | R101: View Document | S101: 45441 | T101: 740334 | U101: - | V101: FORMLABS | W101: PO: 740334 Vendor: FORMLABS Amount: 379.36 | X101: FORMLABS | Y101: 0 | Z101: 379.36 | AA101: -368.54
N102: 45447 | O102: PRNC | P102: 28030362 | Q102: 01 | R102: View Document | S102: 45447 | T102: 753373 | U102: - | V102: FISHER SCIENTIFIC COMPANY LLC | W102: PO: 753373 Vendor: FISHER SCIENTIFIC COMPANY LLC Account: UA 1101935 Amount: 931.84 Pay Date: 06/12/2024 | X102: FISHER SCIENTIFIC COMPANY LLC | Y102: 0 | Z102: 931.84 | AA102: -931.84
...

Sheet 1101935 FY25
B2: INCOME AND EXPENSE REPORT | L2: TRANSACTION REPORT | AC2: PAYROLL REPORT
B4: Account Number | C4: Consolidation Object Name | D4: Object Code | E4: Object Code Name | F4: Current Budget | G4: Fiscal Year Actuals | H4: Inception to Date | I4: Open Encumbrances | J4: Balance Available | L4: Object Code | M4: Object Code Name | N4: Transaction Date | O4: Document | P4: Document Number | Q4: Origin | R4: e-Doc Link | S4: Post Date | T4: Reference Document Number | U4: Organization Document Number | V4: Entry | W4: Document Description | X4: Vendor Name | Y4: Current Budget Amount | Z4: Current Month Actuals | AA4: Encumbrance Amount | AC4: Account Number | AD4: Sub Account Number | AE4: Employee Name | AF4: Position Number | AG4: Object Code | AH4: Object Code Name | AI4: Pay Period Earn Date | AJ4: Document Type Code | AK4: Job FTE | AL4: Hours Worked | AM4: Expenditure Amount
B5: 1101935 | C5: OTHER REVENUE | D5: 0899 | E5: Net Revenues - FSO Only | F5: 0 | G5: 0 | H5: 0 | I5: 0 | J5: 0 | L5: 0932 | M5: Budget Adjustment Income Transfer | N5: 45695 | O5: TF | P5: B217367 | Q5: BO | R5: Link Not Available | S5: 45695 | T5: - | U5: 2025020750 | V5: FY25 ENGR COMMITMENT TO MCGHEE STARTUP P | W5: - | X5: - | Y5: 0 | Z5: -219462 | AA5: 0 | AC5: 1101935 | AD5: - | AE5: Declercq,Gabriel Leonard Galahad | AF5: 2004160 | AG5: 1340 | AH5: Student Wages (ere1) | AI5: 45536 | AJ5: LLPR | AK5: 0.625 | AL5: 48 | AM5: 696
C6: TRANSFER OF FUNDS | D6: 0932 | E6: Budget Adjustment Income Transfer | F6: 0 | G6: -219462 | H6: -219462 | I6: 0 | J6: 219462 | L6: 0932 Total | Y6: 0 | Z6: -219462 | AA6: 0 | AI6: 45550 | AJ6: LLPR | AK6: 0.625 | AL6: 72 | AM6: 1044
C7: INCOME Total | F7: 0 | G7: -219462 | H7: -219462 | I7: 0 | J7: 219462 | L7: 1000 | M7: Personal Services-Budget | N7: 45695 | O7: BTR | P7: B217367 | Q7: BO | R7: Link Not Available | S7: 45695 | T7: - | U7: 2025020750 | V7: FY25 ENGR COMMITMENT TO MCGHEE STARTUP P | W7: - | X7: - | Y7: 219462 | Z7: 0 | AA7: 0 | AI7: 45564 | AJ7: LLPR | AK7: 0.625 | AL7: 35 | AM7: 507.5
C8: PERSONAL SERVICES | D8: 1000 | E8: Personal Services-Budget | F8: 219462 | G8: 0 | H8: 0 | I8: 0 | J8: 219462 | L8: 1000 Total | Y8: 219462 | Z8: 0 | AA8: 0 | AI8: 45578 | AJ8: LLPR | AK8: 0.625 | AL8: 37 | AM8: 536.5
D9: 1190 | E9: Graduate Asst/Assoc Salaries (ere 8) | F9: 0 | G9: 0 | H9: 0 | I9: 0 | J9: 0 | L9: 1190 | M9: Graduate Asst/Assoc Salaries (ere 8) | N9: 45679 | O9: LLPE | P9: 20250122200001 | Q9: UE | R9: Link Not Available | S9: 45679 | T9: - | U9: - | V9: PAYROLL ENCUMBRANCES | W9: - | X9: - | Y9: 0 | Z9: 0 | AA9: 10537 | AI9: 45592 | AJ9: LLPR | AK9: 0.625 | AL9: 36.5 | AM9: 529.25
D10: 1212 | E10: Supp Com Regular App/Fac (ere 4) | F10: 0 | G10: 23479.72 | H10: 23479.72 | I10: 0 | J10: -23479.72 | N10: 45693 | O10: LLPE | P10: 20250205200001 | Q10: MF | R10: Link Not Available | S10: 45693 | T10: - | U10: - | V10: PAYROLL ENCUMBRANCES | W10: - | X10: - | Y10: 0 | Z10: 0 | AA10: -1171 | AI10: 45606 | AJ10: LLPR | AK10: 0.625 | AL10: 37 | AM10: 536.5
D11: 1213 | E11: Supp Comp Grad (ere 8) | F11: 0 | G11: 3098.54 | H11: 3098.54 | I11: 0 | J11: -3098.54 | O11: LLPR | P11: 20250207100001 | Q11: UE | R11: Link Not Available | S11: 45693 | T11: - | U11: 07 | V11: NORMAL PAYROLL ACTIVITY | W11: - | X11: - | Y11: 0 | Z11: 2341.5 | AA11: 0 | AI11: 45620 | AJ11: LLPR | AK11: 0.625 | AL11: 11.5 | AM11: 166.75
D12: 1340 | E12: Student Wages (ere1) | F12: 0 | G12: 10801.1 | H12: 10801.1 | I12: 0 | J12: -10801.1 | N12: 45695 | O12: ST | P12: 30115321 | Q12: 01 | R12: View Document | S12: 45695 | T12: - | U12: - | V12: Alia Rose Starman | W12: Salary Expense Transfer - Salary Expense Transfer Alia Starman | X12: - | Y12: 0 | Z12: -2341.5 | AA12: 0 | AI12: 45634 | AJ12: LLPR | AK12: 0.625 | AL12: 39.5 | AM12: 572.75
D13: 2117 | E13: Student Employees ERE | F13: 0 | G13: 216.04 | H13: 216.04 | I13: 0 | J13: -216.04 | N13: 45698 | O13: LLPE | P13: 20250210200000 | Q13: MF | R13: Link Not Available | S13: 45698 | T13: - | U13: - | V13: PAYROLL ENCUMBRANCES | W13: - | X13: - | Y13: 0 | Z13: 0 | AA13: -9366 | AI13: 45648 | AJ13: LLPR | AK13: 0.625 | AL13: 68 | AM13: 986
D14: 2119 | E14: Graduate Assistants ERE | F14: 0 | G14: 402.8 | H14: 402.8 | I14: 0 | J14: -402.8 | L14: 1190 Total | Y14: 0 | Z14: 0 | AA14: 0 | AI14: 45662 | AJ14: LLPR | AK14: 0.625 | AL14: 33 | AM14: 485.1
D15: 2121 | E15: Employee Full-Benefit ERE | F15: 0 | G15: 7513.52 | H15: 7513.52 | I15: 0 | J15: -7513.52 | L15: 1212 | M15: Supp Com Regular App/Fac (ere 4) | N15: 45481 | O15: LLPE | P15: 20240707200001 | Q15: UE | R15: Link Not Available | S15: 45481 | T15: - | U15: - | V15: PAYROLL ENCUMBRANCES | W15: - | X15: - | Y15: 0 | Z15: 0 | AA15: 563 | AI15: 45676 | AJ15: LLPR | AK15: 0.625 | AL15: 13 | AM15: 191.1
C16: GENERAL EXPENSES | D16: 3510 | E16: R/M Services-Buildings | F16: 0 | G16: 341.88 | H16: 341.88 | I16: 0 | J16: -341.88 | N16: 45490 | O16: LLPE | P16: 20240717200001 | Q16: MF | R16: Link Not Available | S16: 45490 | T16: - | U16: - | V16: PAYROLL ENCUMBRANCES | W16: - | X16: - | Y16: 0 | Z16: 0 | AA16: -81 | AI16: 45690 | AJ16: LLPR | AK16: 0.625 | AL16: 32 | AM16: 470.4
D17: 3870 | E17: Express Shipping | F17: 0 | G17: 95.32 | H17: 95.32 | I17: 0 | J17: -95.32 | N17: 45497 | O17: LLPE | P17: 20240724200001 | Q17: MF | R17: Link Not Available | S17: 45497 | T17: - | U17: - | V17: PAYROLL ENCUMBRANCES | W17: - | X17: - | Y17: 0 | Z17: 0 | AA17: -160 | AI17: 45704 | AJ17: LLPR | AK17: 0.625 | AL17: 55 | AM17: 808.5
D18: 4620 | E18: Software Licenses/Royalties | F18: 0 | G18: 962.34 | H18: 962.34 | I18: 0 | J18: -962.34 | O18: LLPR | P18: 20240726100001 | Q18: UE | R18: Link Not Available | S18: 45497 | T18: - | U18: 01 | V18: NORMAL PAYROLL ACTIVITY | W18: - | X18: - | Y18: 0 | Z18: 3216.4 | AA18: 0 | AI18: 45718 | AJ18: LLPR | AK18: 0.625 | AL18: 43.5 | AM18: 639.45
D19: 4840 | E19: Printing & Lithography | F19: 0 | G19: 128.91 | H19: 128.91 | I19: 0 | J19: -128.91 | N19: 45511 | O19: LLPE | P19: 20240807200001 | Q19: MF | R19: Link Not Available | S19: 45511 | T19: - | U19: - | V19: PAYROLL ENCUMBRANCES | W19: - | X19: - | Y19: 0 | Z19: 0 | AA19: -161 | AI19: 45732 | AJ19: LLPR | AK19: 0.625 | AL19: 42.5 | AM19: 624.75
D20: 5150 | E20: Data Processing Supplies | F20: 0 | G20: 102.69 | H20: 102.69 | I20: 0 | J20: -102.69 | O20: LLPR | P20: 20240809100001 | Q20: UE | R20: Link Not Available | S20: 45511 | T20: - | U20: 01 | V20: NORMAL PAYROLL ACTIVITY | W20: - | X20: - | Y20: 0 | Z20: 3216.4 | AA20: 0 | AI20: 45746 | AJ20: LLPR | AK20: 0.625 | AL20: 54 | AM20: 793.8
D21: 5180 | E21: Educational Supplies | F21: 0 | G21: 308.2 | H21: 308.2 | I21: 0 | J21: -308.2 | N21: 45525 | O21: LLPE | P21: 20240821200000 | Q21: MF | R21: Link Not Available | S21: 45525 | T21: - | U21: - | V21: PAYROLL ENCUMBRANCES | W21: - | X21: - | Y21: 0 | Z21: 0 | AA21: -161 | AI21: 45760 | AJ21: LLPR | AK21: 0.625 | AL21: 39 | AM21: 573.3
D22: 5220 | E22: Housekeeping Supplies | F22: 0 | G22: 107.62 | H22: 107.62 | I22: 0 | J22: -107.62 | O22: LLPR | P22: 20240823100001 | Q22: UE | R22: Link Not Available | S22: 45525 | T22: - | U22: 02 | V22: NORMAL PAYROLL ACTIVITY | W22: - | X22: - | Y22: 0 | Z22: 3216.4 | AA22: 0 | AI22: 45774 | AJ22: LLPR | AK22: 0.625 | AL22: 23 | AM22: 338.1
D23: 5230 | E23: Office Supplies | F23: 0 | G23: 2433.98 | H23: 2433.98 | I23: 0 | J23: -2433.98 | N23: 45796 | O23: LLPE | P23: 20250519200001 | Q23: UE | R23: Link Not Available | S23: 45796 | T23: - | U23: - | V23: PAYROLL ENCUMBRANCES | W23: - | X23: - | Y23: 0 | Z23: 0 | AA23: 418 | AI23: 45788 | AJ23: LLPR | AK23: 0.625 | AL23: 20.5 | AM23: 301.35
D24: 5260 | E24: R/M Supplies - Shop | F24: 0 | G24: 170.25 | H24: 170.25 | I24: 0 | J24: -170.25 | N24: 45819 | O24: LLPE | P24: 20250611200001 | Q24: MF | R24: Link Not Available | S24: 45819 | T24: - | U24: - | V24: PAYROLL ENCUMBRANCES | W24: - | X24: - | Y24: 0 | Z24: 0 | AA24: -161 | AG24: 1340 Total | AL24: 740 | AM24: 10801.1
D25: 5290 | E25: Research Supplies/Medical - Laboratory | F25: 0 | G25: 73587.02 | H25: 73587.02 | I25: 280.92 | J25: -73867.94 | O25: LLPR | P25: 20250613100001 | Q25: UE | R25: Link Not Available | S25: 45819 | T25: - | U25: 11 | V25: NORMAL PAYROLL ACTIVITY | W25: - | X25: - | Y25: 0 | Z25: 2573.12 | AA25: 0 | AG25: 2117 | AH25: Student Employees ERE | AI25: 45536 | AJ25: LLPR | AK25: 0.625 | AL25: 0 | AM25: 13.92
D26: 5490 | E26: Operating Supplies - Other | F26: 0 | G26: 4098.69 | H26: 4098.69 | I26: 0 | J26: -4098.69 | U26: 12 | V26: NORMAL PAYROLL ACTIVITY | W26: - | X26: - | Y26: 0 | Z26: 3216.4 | AA26: 0 | AI26: 45550 | AJ26: LLPR | AK26: 0.625 | AL26: 0 | AM26: 20.88
D27: 5520 | E27: Conference Registration Fees | F27: 0 | G27: 1044 | H27: 1044 | I27: 0 | J27: -1044 | N27: 45833 | O27: LLPE | P27: 20250625200001 | Q27: MF | R27: Link Not Available | S27: 45833 | T27: - | U27: - | V27: PAYROLL ENCUMBRANCES | W27: - | X27: - | Y27: 0 | Z27: 0 | AA27: -161 | AI27: 45564 | AJ27: LLPR | AK27: 0.625 | AL27: 0 | AM27: 10.15
D28: 5535 | E28: Purchasing Transaction Fees | F28: 0 | G28: 76.99 | H28: 76.99 | I28: 0 | J28: -76.99 | O28: LLPR | P28: 20250627100001 | Q28: UE | R28: Link Not Available | S28: 45833 | T28: - | U28: 12 | V28: NORMAL PAYROLL ACTIVITY | W28: - | X28: - | Y28: 0 | Z28: 5789.52 | AA28: 0 | AI28: 45578 | AJ28: LLPR | AK28: 0.625 | AL28: 0 | AM28: 10.73
D29: 5540 | E29: Dues | F29: 0 | G29: 265 | H29: 265 | I29: 0 | J29: -265 | N29: 45847 | O29: LLPR | P29: 20250711100001 | Q29: UE | R29: Link Not Available | S29: 45847 | T29: - | U29: 12 | V29: NORMAL PAYROLL ACTIVITY | W29: - | X29: - | Y29: 0 | Z29: 2251.48 | AA29: 0 | AI29: 45592 | AJ29: LLPR | AK29: 0.625 | AL29: 0 | AM29: 10.59
D30: 5560 | E30: Freight In/Out - (Noncapital related) | F30: 0 | G30: 434.94 | H30: 434.94 | I30: 0 | J30: -434.94 | N30: 45849 | O30: LLPE | P30: 20250630200000 | Q30: MF | R30: Link Not Available | S30: 45849 | T30: - | U30: - | V30: PAYROLL ENCUMBRANCES | W30: - | X30: - | Y30: 0 | Z30: 0 | AA30: -96 | AI30: 45606 | AJ30: LLPR | AK30: 0.625 | AL30: 0 | AM30: 10.73
D31: 5610 | E31: Subscriptions | F31: 0 | G31: 16.47 | H31: 16.47 | I31: 0 | J31: -16.47 | L31: 1212 Total | Y31: 0 | Z31: 23479.72 | AA31: 0 | AI31: 45620 | AJ31: LLPR | AK31: 0.625 | AL31: 0 | AM31: 3.34
D32: 5760 | E32: Noncapitalized Equipment - EDP | F32: 0 | G32: 7314.26 | H32: 7314.26 | I32: 0 | J32: -7314.26 | L32: 1213 | M32: Supp Comp Grad (ere 8) | N32: 45791 | O32: LLPE | P32: 20250514200001 | Q32: UE | R32: Link Not Available | S32: 45791 | T32: - | U32: - | V32: PAYROLL ENCUMBRANCES | W32: - | X32: - | Y32: 0 | Z32: 0 | AA32: 102 | AI32: 45634 | AJ32: LLPR | AK32: 0.625 | AL32: 0 | AM32: 11.45
D33: 5770 | E33: Noncapitalized Equipment - Other | F33: 0 | G33: 483.2 | H33: 483.2 | I33: 0 | J33: -483.2 | N33: 45819 | O33: LLPE | P33: 20250611200001 | Q33: MF | R33: Link Not Available | S33: 45819 | T33: - | U33: - | V33: PAYROLL ENCUMBRANCES | W33: - | X33: - | Y33: 0 | Z33: 0 | AA33: -39 | AI33: 45648 | AJ33: LLPR | AK33: 0.625 | AL33: 0 | AM33: 19.72
D34: 5780 | E34: Miscellaneous - Other Operating | F34: 0 | G34: 142.54 | H34: 142.54 | I34: 0 | J34: -142.54 | O34: LLPR | P34: 20250613100001 | Q34: UE | R34: Link Not Available | S34: 45819 | T34: - | U34: 11 | V34: NORMAL PAYROLL ACTIVITY | W34: - | X34: - | Y34: 0 | Z34: 588.33 | AA34: 0 | AI34: 45662 | AJ34: LLPR | AK34: 0.625 | AL34: 0 | AM34: 9.7
D35: 5899 | E35: Net Expenses - FSO Only | F35: 0 | G35: 0 | H35: 0 | I35: 0 | J35: 0 | U35: 12 | V35: NORMAL PAYROLL ACTIVITY | W35: - | X35: - | Y35: 0 | Z35: 588.33 | AA35: 0 | AI35: 45676 | AJ35: LLPR | AK35: 0.625 | AL35: 0 | AM35: 3.82
C36: TRAVEL | D36: 6240 | E36: TRAVEL-OUT STATE | F36: 0 | G36: 2044.72 | H36: 2044.72 | I36: 0 | J36: -2044.72 | N36: 45833 | O36: LLPE | P36: 20250625200001 | Q36: MF | R36: Link Not Available | S36: 45833 | T36: - | U36: - | V36: PAYROLL ENCUMBRANCES | W36: - | X36: - | Y36: 0 | Z36: 0 | AA36: -39 | AI36: 45690 | AJ36: LLPR | AK36: 0.625 | AL36: 0 | AM36: 9.41
D37: 6241 | E37: TRAVEL-OUT OF STATE AIRLINES | F37: 0 | G37: 444.47 | H37: 444.47 | I37: 0 | J37: -444.47 | O37: LLPR | P37: 20250627100001 | Q37: UE | R37: Link Not Available | S37: 45833 | T37: - | U37: 12 | V37: NORMAL PAYROLL ACTIVITY | W37: - | X37: - | Y37: 0 | Z37: 1176.66 | AA37: 0 | AI37: 45704 | AJ37: LLPR | AK37: 0.625 | AL37: 0 | AM37: 16.17
D38: 6242 | E38: TRAVEL-OUT STATE HOTEL | F38: 0 | G38: 72 | H38: 72 | I38: 0 | J38: -72 | N38: 45847 | O38: LLPR | P38: 20250711100001 | Q38: UE | R38: Link Not Available | S38: 45847 | T38: - | U38: 12 | V38: NORMAL PAYROLL ACTIVITY | W38: - | X38: - | Y38: 0 | Z38: 745.22 | AA38: 0 | AI38: 45718 | AJ38: LLPR | AK38: 0.625 | AL38: 0 | AM38: 12.79
C39: CAPITAL | D39: 7690 | E39: Scientific Equipment | F39: 0 | G39: 13409.23 | H39: 13409.23 | I39: 0 | J39: -13409.23 | N39: 45849 | O39: LLPE | P39: 20250630200000 | Q39: MF | R39: Link Not Available | S39: 45849 | T39: - | U39: - | V39: PAYROLL ENCUMBRANCES | W39: - | X39: - | Y39: 0 | Z39: 0 | AA39: -24 | AI39: 45732 | AJ39: LLPR | AK39: 0.625 | AL39: 0 | AM39: 12.5
C40: EXPENSES Total | F40: 219462 | G40: 153596.44 | H40: 153596.44 | I40: 280.92 | J40: 65584.64 | L40: 1213 Total | Y40: 0 | Z40: 3098.54 | AA40: 0 | AI40: 45746 | AJ40: LLPR | AK40: 0.625 | AL40: 0 | AM40: 15.88
B41: Grand Total | F41: 219462 | G41: -65865.56 | H41: -65865.56 | I41: 280.92 | J41: 285046.64 | L41: 1340 | M41: Student Wages (ere1) | N41: 45525 | O41: LLPE | P41: 20240821200001 | Q41: UE | R41: Link Not Available | S41: 45525 | T41: - | U41: - | V41: PAYROLL ENCUMBRANCES | W41: - | X41: - | Y41: 0 | Z41: 0 | AA41: 16385 | AI41: 45760 | AJ41: LLPR | AK41: 0.625 | AL41: 0 | AM41: 11.47
N42: 45539 | O42: LLPE | P42: 20240904200001 | Q42: MF | R42: Link Not Available | S42: 45539 | T42: - | U42: - | V42: PAYROLL ENCUMBRANCES | W42: - | X42: - | Y42: 0 | Z42: 0 | AA42: -725 | AI42: 45774 | AJ42: LLPR | AK42: 0.625 | AL42: 0 | AM42: 6.76
O43: LLPR | P43: 20240906100001 | Q43: UE | R43: Link Not Available | S43: 45539 | T43: - | U43: 02 | V43: NORMAL PAYROLL ACTIVITY | W43: - | X43: - | Y43: 0 | Z43: 696 | AA43: 0 | AI43: 45788 | AJ43: LLPR | AK43: 0.625 | AL43: 0 | AM43: 6.03
N44: 45553 | O44: LLPE | P44: 20240918200001 | Q44: MF | R44: Link Not Available | S44: 45553 | T44: - | U44: - | V44: PAYROLL ENCUMBRANCES | W44: - | X44: - | Y44: 0 | Z44: 0 | AA44: -725 | AG44: 2117 Total | AL44: 0 | AM44: 216.04
N45: 45567 | O45: LLPE | P45: 20241002200001 | Q45: MF | R45: Link Not Available | S45: 45567 | T45: - | U45: - | V45: PAYROLL ENCUMBRANCES | W45: - | X45: - | Y45: 0 | Z45: 0 | AA45: -725 | AE45: McGhee,Alexander | AF45: 1867411 | AG45: 1212 | AH45: Supp Com Regular App/Fac (ere 4) | AI45: 45494 | AJ45: LLPR | AK45: 0.025 | AL45: 40 | AM45: 3216.4
N46: 45581 | O46: LLPE | P46: 20241016200001 | Q46: MF | R46: Link Not Available | S46: 45581 | T46: - | U46: - | V46: PAYROLL ENCUMBRANCES | W46: - | X46: - | Y46: 0 | Z46: 0 | AA46: -725 | AI46: 45508 | AJ46: LLPR | AK46: 0.025 | AL46: 40 | AM46: 3216.4
O47: LLPR | P47: 20241018100001 | Q47: UE | R47: Link Not Available | S47: 45581 | T47: - | U47: 03 | V47: NORMAL PAYROLL ACTIVITY | W47: - | X47: - | Y47: 0 | Z47: 561.15 | AA47: 0 | AI47: 45522 | AJ47: LLPR | AK47: 0.025 | AL47: 40 | AM47: 3216.4
U48: 04 | V48: NORMAL PAYROLL ACTIVITY | W48: - | X48: - | Y48: 0 | Z48: 482.85 | AA48: 0 | AI48: 45816 | AJ48: LLPR | AK48: 0.025 | AL48: 72 | AM48: 5789.52
N49: 45595 | O49: LLPR | P49: 20241101100001 | Q49: UE | R49: Link Not Available | S49: 45595 | T49: - | U49: 04 | V49: NORMAL PAYROLL ACTIVITY | W49: - | X49: - | Y49: 0 | Z49: 790.25 | AA49: 0 | AI49: 45830 | AJ49: LLPR | AK49: 0.025 | AL49: 72 | AM49: 5789.52
N50: 45597 | O50: LLPE | P50: 20241101200001 | Q50: MF | R50: Link Not Available | S50: 45597 | T50: - | U50: - | V50: PAYROLL ENCUMBRANCES | W50: - | X50: - | Y50: 0 | Z50: 0 | AA50: -725 | AI50: 45844 | AJ50: LLPR | AK50: 0.025 | AL50: 28 | AM50: 2251.48
N51: 45609 | O51: LLPE | P51: 20241113200001 | Q51: MF | R51: Link Not Available | S51: 45609 | T51: - | U51: - | V51: PAYROLL ENCUMBRANCES | W51: - | X51: - | Y51: 0 | Z51: 0 | AA51: -725 | AG51: 1212 Total | AL51: 292 | AM51: 23479.72
O52: LLPR | P52: 20241115100001 | Q52: UE | R52: Link Not Available | S52: 45609 | T52: - | U52: 04 | V52: NORMAL PAYROLL ACTIVITY | W52: - | X52: - | Y52: 0 | Z52: 887.4 | AA52: 0 | AG52: 2121 | AH52: Employee Full-Benefit ERE | AI52: 45494 | AJ52: LLPR | AK52: 0.025 | AL52: 0 | AM52: 1029.25
U53: 05 | V53: NORMAL PAYROLL ACTIVITY | W53: - | X53: - | Y53: 0 | Z53: 156.6 | AA53: 0 | AI53: 45508 | AJ53: LLPR | AK53: 0.025 | AL53: 0 | AM53: 1029.25
N54: 45621 | O54: LLPE | P54: 20241125200001 | Q54: MF | R54: Link Not Available | S54: 45621 | T54: - | U54: - | V54: PAYROLL ENCUMBRANCES | W54: - | X54: - | Y54: 0 | Z54: 0 | AA54: -725 | AI54: 45522 | AJ54: LLPR | AK54: 0.025 | AL54: 0 | AM54: 1029.25
O55: LLPR | P55: 20241127100001 | Q55: UE | R55: Link Not Available | S55: 45621 | T55: - | U55: 05 | V55: NORMAL PAYROLL ACTIVITY | W55: - | X55: - | Y55: 0 | Z55: 166.75 | AA55: 0 | AI55: 45816 | AJ55: LLPR | AK55: 0.025 | AL55: 0 | AM55: 1852.65
N56: 45637 | O56: LLPE | P56: 20241211200001 | Q56: MF | R56: Link Not Available | S56: 45637 | T56: - | U56: - | V56: PAYROLL ENCUMBRANCES | W56: - | X56: - | Y56: 0 | Z56: 0 | AA56: -725 | AI56: 45830 | AJ56: LLPR | AK56: 0.025 | AL56: 0 | AM56: 1852.65
O57: LLPR | P57: 20241213100001 | Q57: UE | R57: Link Not Available | S57: 45637 | T57: - | U57: 05 | V57: NORMAL PAYROLL ACTIVITY | W57: - | X57: - | Y57: 0 | Z57: 467.63 | AA57: 0 | AI57: 45844 | AJ57: LLPR | AK57: 0.025 | AL57: 0 | AM57: 720.47
U58: 06 | V58: NORMAL PAYROLL ACTIVITY | W58: - | X58: - | Y58: 0 | Z58: 192.12 | AA58: 0 | AG58: 2121 Total | AL58: 0 | AM58: 7513.52
N59: 45646 | O59: LLPE | P59: 20241220200001 | Q59: MF | R59: Link Not Available | S59: 45646 | T59: - | U59: - | V59: PAYROLL ENCUMBRANCES | W59: - | X59: - | Y59: 0 | Z59: 0 | AA59: -725 | AE59: Starman,Alia Rose | AF59: 2059830 | AG59: 1213 | AH59: Supp Comp Grad (ere 8) | AI59: 45816 | AJ59: LLPR | AK59: 0.025 | AL59: 40.2 | AM59: 1176.66
O60: LLPR | P60: 20241227100001 | Q60: UE | R60: Link Not Available | S60: 45646 | T60: - | U60: 06 | V60: NORMAL PAYROLL ACTIVITY | W60: - | X60: - | Y60: 0 | Z60: 1174.5 | AA60: 0 | AI60: 45830 | AJ60: LLPR | AK60: 0.025 | AL60: 40.2 | AM60: 1176.66
N61: 45649 | O61: LLPE | P61: 20241223200001 | Q61: MF | R61: Link Not Available | S61: 45649 | T61: - | U61: - | V61: PAYROLL ENCUMBRANCES | W61: - | X61: - | Y61: 0 | Z61: 0 | AA61: 136 | AI61: 45844 | AJ61: LLPR | AK61: 0.025 | AL61: 25.46 | AM61: 745.22
N62: 45665 | O62: LLPE | P62: 20250108200001 | Q62: MF | R62: Link Not Available | S62: 45665 | T62: - | U62: - | V62: PAYROLL ENCUMBRANCES | W62: - | X62: - | Y62: 0 | Z62: 0 | AA62: -735 | AG62: 1213 Total | AL62: 105.86 | AM62: 3098.54
N63: 45679 | O63: LLPE | P63: 20250122200001 | Q63: MF | R63: Link Not Available | S63: 45679 | T63: - | U63: - | V63: PAYROLL ENCUMBRANCES | W63: - | X63: - | Y63: 0 | Z63: 0 | AA63: -735 | AG63: 2119 | AH63: Graduate Assistants ERE | AI63: 45816 | AJ63: LLPR | AK63: 0.025 | AL63: 0 | AM63: 152.96
O64: LLPR | P64: 20250124100001 | Q64: UE | R64: Link Not Available | S64: 45679 | T64: - | U64: 07 | V64: NORMAL PAYROLL ACTIVITY | W64: - | X64: - | Y64: 0 | Z64: 676.2 | AA64: 0 | AI64: 45830 | AJ64: LLPR | AK64: 0.025 | AL64: 0 | AM64: 152.96
N65: 45693 | O65: LLPE | P65: 20250205200001 | Q65: MF | R65: Link Not Available | S65: 45693 | T65: - | U65: - | V65: PAYROLL ENCUMBRANCES | W65: - | X65: - | Y65: 0 | Z65: 0 | AA65: -735 | AI65: 45844 | AJ65: LLPR | AK65: 0.025 | AL65: 0 | AM65: 96.88
O66: LLPR | P66: 20250207100001 | Q66: UE | R66: Link Not Available | S66: 45693 | T66: - | U66: 07 | V66: NORMAL PAYROLL ACTIVITY | W66: - | X66: - | Y66: 0 | Z66: 470.4 | AA66: 0 | AG66: 2119 Total | AL66: 0 | AM66: 402.8
N67: 45707 | O67: LLPE | P67: 20250219200001 | Q67: MF | R67: Link Not Available | S67: 45707 | T67: - | U67: - | V67: PAYROLL ENCUMBRANCES | W67: - | X67: - | Y67: 0 | Z67: 0 | AA67: -735 | AG67: 2120 | AH67: Graduate Assistants Tuition Remission ER | AI67: 45816 | AJ67: LLPR | AK67: 0.025 | AL67: 0 | AM67: 0
O68: LLPR | P68: 20250221100001 | Q68: UE | R68: Link Not Available | S68: 45707 | T68: - | U68: 08 | V68: NORMAL PAYROLL ACTIVITY | W68: - | X68: - | Y68: 0 | Z68: 808.5 | AA68: 0 | AI68: 45830 | AJ68: LLPR | AK68: 0.025 | AL68: 0 | AM68: 0
N69: 45721 | O69: LLPE | P69: 20250305200001 | Q69: MF | R69: Link Not Available | S69: 45721 | T69: - | U69: - | V69: PAYROLL ENCUMBRANCES | W69: - | X69: - | Y69: 0 | Z69: 0 | AA69: -735 | AI69: 45844 | AJ69: LLPR | AK69: 0.025 | AL69: 0 | AM69: 0
O70: LLPR | P70: 20250307100001 | Q70: UE | R70: Link Not Available | S70: 45721 | T70: - | U70: 08 | V70: NORMAL PAYROLL ACTIVITY | W70: - | X70: - | Y70: 0 | Z70: 639.45 | AA70: 0 | AG70: 2120 Total | AL70: 0 | AM70: 0
N71: 45735 | O71: LLPE | P71: 20250319200001 | Q71: MF | R71: Link Not Available | S71: 45735 | T71: - | U71: - | V71: PAYROLL ENCUMBRANCES | W71: - | X71: - | Y71: 0 | Z71: 0 | AA71: -735 | AF71: 2061789 | AG71: 1190 | AH71: Graduate Asst/Assoc Salaries (ere 8) | AI71: 1 | AJ71: ST | AK71: 0.5 | AL71: 0 | AM71: -2341.5
N72: 45749 | O72: LLPE | P72: 20250402200001 | Q72: MF | R72: Link Not Available | S72: 45749 | T72: - | U72: - | V72: PAYROLL ENCUMBRANCES | W72: - | X72: - | Y72: 0 | Z72: 0 | AA72: -735 | AI72: 45676 | AJ72: LLPR | AK72: 0.5 | AL72: 20 | AM72: 1170.75
O73: LLPR | P73: 20250404100001 | Q73: UE | R73: Link Not Available | S73: 45749 | T73: - | U73: 09 | V73: NORMAL PAYROLL ACTIVITY | W73: - | X73: - | Y73: 0 | Z73: 1418.55 | AA73: 0 | AI73: 45690 | AJ73: LLPR | AK73: 0.5 | AL73: 20 | AM73: 1170.75
N74: 45763 | O74: LLPE | P74: 20250416200001 | Q74: MF | R74: Link Not Available | S74: 45763 | T74: - | U74: - | V74: PAYROLL ENCUMBRANCES | W74: - | X74: - | Y74: 0 | Z74: 0 | AA74: -735 | AG74: 1190 Total | AL74: 40 | AM74: 0
N75: 45777 | O75: LLPR | P75: 20250502100001 | Q75: UE | R75: Link Not Available | S75: 45777 | T75: - | U75: 10 | V75: NORMAL PAYROLL ACTIVITY | W75: - | X75: - | Y75: 0 | Z75: 823.2 | AA75: 0 | AG75: 2119 | AH75: Graduate Assistants ERE | AI75: 1 | AJ75: ST | AK75: 0.5 | AL75: 0 | AM75: -304.4
N76: 45778 | O76: LLPE | P76: 20250501200001 | Q76: MF | R76: Link Not Available | S76: 45778 | T76: - | U76: - | V76: PAYROLL ENCUMBRANCES | W76: - | X76: - | Y76: 0 | Z76: 0 | AA76: -735 | AI76: 45676 | AJ76: LLPR | AK76: 0.5 | AL76: 0 | AM76: 152.2
N77: 45791 | O77: LLPE | P77: 20250514200001 | Q77: MF | R77: Link Not Available | S77: 45791 | T77: - | U77: - | V77: PAYROLL ENCUMBRANCES | W77: - | X77: - | Y77: 0 | Z77: 0 | AA77: -735 | AI77: 45690 | AJ77: LLPR | AK77: 0.5 | AL77: 0 | AM77: 152.2
N78: 45793 | O78: LLPE | P78: 20250516200001 | Q78: MF | R78: Link Not Available | S78: 45793 | T78: - | U78: - | V78: PAYROLL ENCUMBRANCES | W78: - | X78: - | Y78: 0 | Z78: 0 | AA78: -2278 | AG78: 2119 Total | AL78: 0 | AM78: 0
N79: 45805 | O79: LLPE | P79: 20250528200000 | Q79: MF | R79: Link Not Available | S79: 45805 | T79: - | U79: - | V79: PAYROLL ENCUMBRANCES | W79: - | X79: - | Y79: 0 | Z79: 0 | AA79: -368 | AG79: 2120 | AH79: Graduate Assistants Tuition Remission ER | AI79: 45676 | AJ79: LLPR | AK79: 0.5 | AL79: 0 | AM79: 0
O80: LLPR | P80: 20250530100001 | Q80: UE | R80: Link Not Available | S80: 45805 | T80: - | U80: 11 | V80: NORMAL PAYROLL ACTIVITY | W80: - | X80: - | Y80: 0 | Z80: 389.55 | AA80: 0 | AI80: 45690 | AJ80: LLPR | AK80: 0.5 | AL80: 0 | AM80: 0
L81: 1340 Total | Y81: 0 | Z81: 10801.1 | AA81: 0 | AG81: 2120 Total | AL81: 0 | AM81: 0
L82: 2117 | M82: Student Employees ERE | N82: 45525 | O82: LLPE | P82: 20240821200001 | Q82: UE | R82: Link Not Available | S82: 45525 | T82: - | U82: - | V82: PAYROLL ENCUMBRANCES | W82: - | X82: - | Y82: 0 | Z82: 0 | AA82: 327.7 | AD82: - Total | AL82: 1177.86 | AM82: 45511.72
N83: 45539 | O83: LLPE | P83: 20240904200001 | Q83: MF | R83: Link Not Available | S83: 45539 | T83: - | U83: - | V83: PAYROLL ENCUMBRANCES | W83: - | X83: - | Y83: 0 | Z83: 0 | AA83: -14.5 | AC83: 1101935 Total | AL83: 1177.86 | AM83: 45511.72
O84: LLPR | P84: 20240906100001 | Q84: UE | R84: Link Not Available | S84: 45539 | T84: - | U84: 02 | V84: NORMAL PAYROLL ACTIVITY | W84: - | X84: - | Y84: 0 | Z84: 13.92 | AA84: 0 | AC84: Grand Total | AL84: 1177.86 | AM84: 45511.72
N85: 45553 | O85: LLPE | P85: 20240918200001 | Q85: MF | R85: Link Not Available | S85: 45553 | T85: - | U85: - | V85: PAYROLL ENCUMBRANCES | W85: - | X85: - | Y85: 0 | Z85: 0 | AA85: -14.5
N86: 45567 | O86: LLPE | P86: 20241002200001 | Q86: MF | R86: Link Not Available | S86: 45567 | T86: - | U86: - | V86: PAYROLL ENCUMBRANCES | W86: - | X86: - | Y86: 0 | Z86: 0 | AA86: -14.5
N87: 45581 | O87: LLPE | P87: 20241016200001 | Q87: MF | R87: Link Not Available | S87: 45581 | T87: - | U87: - | V87: PAYROLL ENCUMBRANCES | W87: - | X87: - | Y87: 0 | Z87: 0 | AA87: -14.5
O88: LLPR | P88: 20241018100001 | Q88: UE | R88: Link Not Available | S88: 45581 | T88: - | U88: 03 | V88: NORMAL PAYROLL ACTIVITY | W88: - | X88: - | Y88: 0 | Z88: 11.22 | AA88: 0
U89: 04 | V89: NORMAL PAYROLL ACTIVITY | W89: - | X89: - | Y89: 0 | Z89: 9.66 | AA89: 0
N90: 45595 | O90: LLPR | P90: 20241101100001 | Q90: UE | R90: Link Not Available | S90: 45595 | T90: - | U90: 04 | V90: NORMAL PAYROLL ACTIVITY | W90: - | X90: - | Y90: 0 | Z90: 15.81 | AA90: 0
N91: 45597 | O91: LLPE | P91: 20241101200001 | Q91: MF | R91: Link Not Available | S91: 45597 | T91: - | U91: - | V91: PAYROLL ENCUMBRANCES | W91: - | X91: - | Y91: 0 | Z91: 0 | AA91: -14.5
N92: 45609 | O92: LLPE | P92: 20241113200001 | Q92: MF | R92: Link Not Available | S92: 45609 | T92: - | U92: - | V92: PAYROLL ENCUMBRANCES | W92: - | X92: - | Y92: 0 | Z92: 0 | AA92: -14.5
O93: LLPR | P93: 20241115100001 | Q93: UE | R93: Link Not Available | S93: 45609 | T93: - | U93: 04 | V93: NORMAL PAYROLL ACTIVITY | W93: - | X93: - | Y93: 0 | Z93: 17.75 | AA93: 0
U94: 05 | V94: NORMAL PAYROLL ACTIVITY | W94: - | X94: - | Y94: 0 | Z94: 3.13 | AA94: 0
N95: 45621 | O95: LLPE | P95: 20241125200001 | Q95: MF | R95: Link Not Available | S95: 45621 | T95: - | U95: - | V95: PAYROLL ENCUMBRANCES | W95: - | X95: - | Y95: 0 | Z95: 0 | AA95: -14.5
O96: LLPR | P96: 20241127100001 | Q96: UE | R96: Link Not Available | S96: 45621 | T96: - | U96: 05 | V96: NORMAL PAYROLL ACTIVITY | W96: - | X96: - | Y96: 0 | Z96: 3.34 | AA96: 0
N97: 45637 | O97: LLPE | P97: 20241211200001 | Q97: MF | R97: Link Not Available | S97: 45637 | T97: - | U97: - | V97: PAYROLL ENCUMBRANCES | W97: - | X97: - | Y97: 0 | Z97: 0 | AA97: -14.5
O98: LLPR | P98: 20241213100001 | Q98: UE | R98: Link Not Available | S98: 45637 | T98: - | U98: 05 | V98: NORMAL PAYROLL ACTIVITY | W98: - | X98: - | Y98: 0 | Z98: 9.35 | AA98: 0
U99: 06 | V99: NORMAL PAYROLL ACTIVITY | W99: - | X99: - | Y99: 0 | Z99: 3.84 | AA99: 0
N100: 45646 | O100: LLPE | P100: 20241220200001 | Q100: MF | R100: Link Not Available | S100: 45646 | T100: - | U100: - | V100: PAYROLL ENCUMBRANCES | W100: - | X100: - | Y100: 0 | Z100: 0 | AA100: -14.5
O101: LLPR | P101: 20241227100001 | Q101: UE | R101: Link Not Available | S101: 45646 | T101: - | U101: 06 | V101: NORMAL PAYROLL ACTIVITY | W101: - | X101: - | Y101: 0 | Z101: 23.49 | AA101: 0
N102: 45649 | O102: LLPE | P102: 20241223200001 | Q102: MF | R102: Link Not Available | S102: 45649 | T102: - | U102: - | V102: PAYROLL ENCUMBRANCES | W102: - | X102: - | Y102: 0 | Z102: 0 | AA102: 2.72
...

Sheet 1101935 FY26
B2: INCOME AND EXPENSE REPORT | L2: TRANSACTION REPORT | AC2: PAYROLL REPORT
B4: Account Number | C4: Consolidation Object Name | D4: Object Code | E4: Object Code Name | F4: Current Budget | G4: Fiscal Year Actuals | H4: Inception to Date | I4: Open Encumbrances | J4: Balance Available | L4: Object Code | M4: Object Code Name | N4: Transaction Date | O4: Document | P4: Document Number | Q4: Origin | R4: e-Doc Link | S4: Post Date | T4: Reference Document Number | U4: Organization Document Number | V4: Entry | W4: Document Description | X4: Vendor Name | Y4: Current Budget Amount | Z4: Current Month Actuals | AA4: Encumbrance Amount | AC4: Account Number | AD4: Sub Account Number | AE4: Employee Name | AF4: Position Number | AG4: Object Code | AH4: Object Code Name | AI4: Pay Period Earn Date | AJ4: Document Type Code | AK4: Job FTE | AL4: Hours Worked | AM4: Expenditure Amount
B5: 1101935 | C5: PERSONAL SERVICES | D5: 1190 | E5: Graduate Asst/Assoc Salaries (ere 8) | F5: 0 | G5: 2116.87 | H5: 2116.87 | I5: 14133 | J5: -16249.87 | L5: 1190 | M5: Graduate Asst/Assoc Salaries (ere 8) | N5: 45845 | O5: LLPE | P5: 20250706200001 | Q5: UE | R5: Link Not Available | S5: 45845 | T5: - | U5: - | V5: PAYROLL ENCUMBRANCES | W5: - | X5: - | Y5: 0 | Z5: 0 | AA5: 16250 | AC5: 1101935 | AD5: - | AE5: Hancock,Cason Montgomery | AF5: 2078743 | AG5: 1190 | AH5: Graduate Asst/Assoc Salaries (ere 8) | AI5: 45844 | AJ5: LLPR | AK5: 0.5 | AL5: 8 | AM5: 249.04
D6: 1212 | E6: Supp Com Regular App/Fac (ere 4) | F6: 0 | G6: 10614.12 | H6: 10614.12 | I6: 0 | J6: -10614.12 | N6: 45854 | O6: LLPE | P6: 20250716200001 | Q6: MF | R6: Link Not Available | S6: 45854 | T6: - | U6: - | V6: PAYROLL ENCUMBRANCES | W6: - | X6: - | Y6: 0 | Z6: 0 | AA6: -249 | AI6: 45858 | AJ6: LLPR | AK6: 0.5 | AL6: 20 | AM6: 622.61
D7: 1213 | E7: Supp Comp Grad (ere 8) | F7: 0 | G7: 3961.42 | H7: 3961.42 | I7: 0 | J7: -3961.42 | O7: LLPR | P7: 20250711100002 | Q7: UE | R7: Link Not Available | S7: 45854 | T7: - | U7: 01 | V7: NORMAL PAYROLL ACTIVITY | W7: - | X7: - | Y7: 0 | Z7: 249.04 | AA7: 0 | AI7: 45872 | AJ7: LLPR | AK7: 0.5 | AL7: 20 | AM7: 622.61
D8: 2119 | E8: Graduate Assistants ERE | F8: 0 | G8: 790.18 | H8: 790.18 | I8: 1837.29 | J8: -2627.47 | N8: 45861 | O8: LLPE | P8: 20250723200001 | Q8: MF | R8: Link Not Available | S8: 45861 | T8: - | U8: - | V8: PAYROLL ENCUMBRANCES | W8: - | X8: - | Y8: 0 | Z8: 0 | AA8: -623 | AI8: 45886 | AJ8: LLPR | AK8: 0.5 | AL8: 20 | AM8: 622.61
D9: 2121 | E9: Employee Full-Benefit ERE | F9: 0 | G9: 3396.5 | H9: 3396.5 | I9: 0 | J9: -3396.5 | O9: LLPR | P9: 20250725100001 | Q9: UE | R9: Link Not Available | S9: 45861 | T9: - | U9: 01 | V9: NORMAL PAYROLL ACTIVITY | W9: - | X9: - | Y9: 0 | Z9: 622.61 | AA9: 0 | AG9: 1190 Total | AL9: 68 | AM9: 2116.87
C10: GENERAL EXPENSES | D10: 3870 | E10: Express Shipping | F10: 0 | G10: 868.34 | H10: 868.34 | I10: 0 | J10: -868.34 | N10: 45875 | O10: LLPE | P10: 20250806200001 | Q10: MF | R10: Link Not Available | S10: 45875 | T10: - | U10: - | V10: PAYROLL ENCUMBRANCES | W10: - | X10: - | Y10: 0 | Z10: 0 | AA10: -622 | AG10: 2119 | AH10: Graduate Assistants ERE | AI10: 45844 | AJ10: LLPR | AK10: 0.5 | AL10: 0 | AM10: 32.38
D11: 4620 | E11: Software Licenses/Royalties | F11: 0 | G11: 179.4 | H11: 179.4 | I11: 0 | J11: -179.4 | O11: LLPR | P11: 20250808100001 | Q11: UE | R11: Link Not Available | S11: 45875 | T11: - | U11: 01 | V11: NORMAL PAYROLL ACTIVITY | W11: - | X11: - | Y11: 0 | Z11: 560.35 | AA11: 0 | AI11: 45858 | AJ11: LLPR | AK11: 0.5 | AL11: 0 | AM11: 80.94
D12: 5290 | E12: Research Supplies/Medical - Laboratory | F12: 0 | G12: 1551.28 | H12: 1551.28 | I12: 258.66 | J12: -1809.94 | U12: 02 | V12: NORMAL PAYROLL ACTIVITY | W12: - | X12: - | Y12: 0 | Z12: 62.26 | AA12: 0 | AI12: 45872 | AJ12: LLPR | AK12: 0.5 | AL12: 0 | AM12: 80.94
C13: TRAVEL | D13: 6240 | E13: TRAVEL-OUT STATE | F13: 0 | G13: 799.98 | H13: 799.98 | I13: 0 | J13: -799.98 | N13: 45889 | O13: LLPE | P13: 20250820200001 | Q13: MF | R13: Link Not Available | S13: 45889 | T13: - | U13: - | V13: PAYROLL ENCUMBRANCES | W13: - | X13: - | Y13: 0 | Z13: 0 | AA13: -623 | AI13: 45886 | AJ13: LLPR | AK13: 0.5 | AL13: 0 | AM13: 80.94
C14: EXPENSES Total | F14: 0 | G14: 24278.09 | H14: 24278.09 | I14: 16228.95 | J14: -40507.04 | O14: LLPR | P14: 20250822100001 | Q14: UE | R14: Link Not Available | S14: 45889 | T14: - | U14: 02 | V14: NORMAL PAYROLL ACTIVITY | W14: - | X14: - | Y14: 0 | Z14: 622.61 | AA14: 0 | AG14: 2119 Total | AL14: 0 | AM14: 275.2
B15: Grand Total | F15: 0 | G15: 24278.09 | H15: 24278.09 | I15: 16228.95 | J15: -40507.04 | L15: 1190 Total | Y15: 0 | Z15: 2116.87 | AA15: 14133 | AG15: 2120 | AH15: Graduate Assistants Tuition Remission ER | AI15: 45844 | AJ15: LLPR | AK15: 0.5 | AL15: 0 | AM15: 0
L16: 1212 | M16: Supp Com Regular App/Fac (ere 4) | N16: 45845 | O16: LLPE | P16: 20250706200001 | Q16: UE | R16: Link Not Available | S16: 45845 | T16: - | U16: - | V16: PAYROLL ENCUMBRANCES | W16: - | X16: - | Y16: 0 | Z16: 0 | AA16: 547 | AI16: 45858 | AJ16: LLPR | AK16: 0.5 | AL16: 0 | AM16: 0
N17: 45854 | O17: LLPE | P17: 20250716200001 | Q17: MF | R17: Link Not Available | S17: 45854 | T17: - | U17: - | V17: PAYROLL ENCUMBRANCES | W17: - | X17: - | Y17: 0 | Z17: 0 | AA17: -65 | AI17: 45872 | AJ17: LLPR | AK17: 0.5 | AL17: 0 | AM17: 0
O18: LLPR | P18: 20250711100002 | Q18: UE | R18: Link Not Available | S18: 45854 | T18: - | U18: 01 | V18: NORMAL PAYROLL ACTIVITY | W18: - | X18: - | Y18: 0 | Z18: 1929.84 | AA18: 0 | AI18: 45886 | AJ18: LLPR | AK18: 0.5 | AL18: 0 | AM18: 0
N19: 45861 | O19: LLPE | P19: 20250723200001 | Q19: MF | R19: Link Not Available | S19: 45861 | T19: - | U19: - | V19: PAYROLL ENCUMBRANCES | W19: - | X19: - | Y19: 0 | Z19: 0 | AA19: -160 | AG19: 2120 Total | AL19: 0 | AM19: 0
O20: LLPR | P20: 20250725100001 | Q20: UE | R20: Link Not Available | S20: 45861 | T20: - | U20: 01 | V20: NORMAL PAYROLL ACTIVITY | W20: - | X20: - | Y20: 0 | Z20: 3216.4 | AA20: 0 | AE20: McGhee,Alexander | AF20: 1867411 | AG20: 1212 | AH20: Supp Com Regular App/Fac (ere 4) | AI20: 45844 | AJ20: LLPR | AK20: 0.025 | AL20: 24 | AM20: 1929.84
N21: 45875 | O21: LLPE | P21: 20250806200001 | Q21: MF | R21: Link Not Available | S21: 45875 | T21: - | U21: - | V21: PAYROLL ENCUMBRANCES | W21: - | X21: - | Y21: 0 | Z21: 0 | AA21: -161 | AI21: 45858 | AJ21: LLPR | AK21: 0.025 | AL21: 40 | AM21: 3216.4
O22: LLPR | P22: 20250808100001 | Q22: UE | R22: Link Not Available | S22: 45875 | T22: - | U22: 01 | V22: NORMAL PAYROLL ACTIVITY | W22: - | X22: - | Y22: 0 | Z22: 2894.76 | AA22: 0 | AI22: 45872 | AJ22: LLPR | AK22: 0.025 | AL22: 40 | AM22: 3216.4
U23: 02 | V23: NORMAL PAYROLL ACTIVITY | W23: - | X23: - | Y23: 0 | Z23: 321.64 | AA23: 0 | AI23: 45886 | AJ23: LLPR | AK23: 0.025 | AL23: 28 | AM23: 2251.48
N24: 45889 | O24: LLPE | P24: 20250820200000 | Q24: MF | R24: Link Not Available | S24: 45889 | T24: - | U24: - | V24: PAYROLL ENCUMBRANCES | W24: - | X24: - | Y24: 0 | Z24: 0 | AA24: -161 | AG24: 1212 Total | AL24: 132 | AM24: 10614.12
O25: LLPR | P25: 20250822100001 | Q25: UE | R25: Link Not Available | S25: 45889 | T25: - | U25: 02 | V25: NORMAL PAYROLL ACTIVITY | W25: - | X25: - | Y25: 0 | Z25: 2251.48 | AA25: 0 | AG25: 2121 | AH25: Employee Full-Benefit ERE | AI25: 45844 | AJ25: LLPR | AK25: 0.025 | AL25: 0 | AM25: 617.55
L26: 1212 Total | Y26: 0 | Z26: 10614.12 | AA26: 0 | AI26: 45858 | AJ26: LLPR | AK26: 0.025 | AL26: 0 | AM26: 1029.24
L27: 1213 | M27: Supp Comp Grad (ere 8) | N27: 45845 | O27: LLPE | P27: 20250706200001 | Q27: UE | R27: Link Not Available | S27: 45845 | T27: - | U27: - | V27: PAYROLL ENCUMBRANCES | W27: - | X27: - | Y27: 0 | Z27: 0 | AA27: 133 | AI27: 45872 | AJ27: LLPR | AK27: 0.025 | AL27: 0 | AM27: 1029.24
N28: 45854 | O28: LLPE | P28: 20250716200001 | Q28: MF | R28: Link Not Available | S28: 45854 | T28: - | U28: - | V28: PAYROLL ENCUMBRANCES | W28: - | X28: - | Y28: 0 | Z28: 0 | AA28: -15 | AI28: 45886 | AJ28: LLPR | AK28: 0.025 | AL28: 0 | AM28: 720.47
O29: LLPR | P29: 20250711100002 | Q29: UE | R29: Link Not Available | S29: 45854 | T29: - | U29: 01 | V29: NORMAL PAYROLL ACTIVITY | W29: - | X29: - | Y29: 0 | Z29: 431.44 | AA29: 0 | AG29: 2121 Total | AL29: 0 | AM29: 3396.5
N30: 45861 | O30: LLPE | P30: 20250723200001 | Q30: MF | R30: Link Not Available | S30: 45861 | T30: - | U30: - | V30: PAYROLL ENCUMBRANCES | W30: - | X30: - | Y30: 0 | Z30: 0 | AA30: -40 | AE30: Starman,Alia Rose | AF30: 2059830 | AG30: 1213 | AH30: Supp Comp Grad (ere 8) | AI30: 45844 | AJ30: LLPR | AK30: 0.025 | AL30: 14.74 | AM30: 431.44
O31: LLPR | P31: 20250725100001 | Q31: UE | R31: Link Not Available | S31: 45861 | T31: - | U31: 01 | V31: NORMAL PAYROLL ACTIVITY | W31: - | X31: - | Y31: 0 | Z31: 1176.66 | AA31: 0 | AI31: 45858 | AJ31: LLPR | AK31: 0.025 | AL31: 40.2 | AM31: 1176.66
N32: 45875 | O32: LLPE | P32: 20250806200001 | Q32: MF | R32: Link Not Available | S32: 45875 | T32: - | U32: - | V32: PAYROLL ENCUMBRANCES | W32: - | X32: - | Y32: 0 | Z32: 0 | AA32: -39 | AI32: 45872 | AJ32: LLPR | AK32: 0.025 | AL32: 40.2 | AM32: 1176.66
O33: LLPR | P33: 20250808100001 | Q33: UE | R33: Link Not Available | S33: 45875 | T33: - | U33: 01 | V33: NORMAL PAYROLL ACTIVITY | W33: - | X33: - | Y33: 0 | Z33: 1058.99 | AA33: 0 | AI33: 45886 | AJ33: LLPR | AK33: 0.025 | AL33: 40.2 | AM33: 1176.66
U34: 02 | V34: NORMAL PAYROLL ACTIVITY | W34: - | X34: - | Y34: 0 | Z34: 117.67 | AA34: 0 | AG34: 1213 Total | AL34: 135.34 | AM34: 3961.42
N35: 45889 | O35: LLPE | P35: 20250820200000 | Q35: MF | R35: Link Not Available | S35: 45889 | T35: - | U35: - | V35: PAYROLL ENCUMBRANCES | W35: - | X35: - | Y35: 0 | Z35: 0 | AA35: -39 | AG35: 2119 | AH35: Graduate Assistants ERE | AI35: 45844 | AJ35: LLPR | AK35: 0.025 | AL35: 0 | AM35: 56.09
O36: LLPR | P36: 20250822100001 | Q36: UE | R36: Link Not Available | S36: 45889 | T36: - | U36: 02 | V36: NORMAL PAYROLL ACTIVITY | W36: - | X36: - | Y36: 0 | Z36: 1176.66 | AA36: 0 | AI36: 45858 | AJ36: LLPR | AK36: 0.025 | AL36: 0 | AM36: 152.96
L37: 1213 Total | Y37: 0 | Z37: 3961.42 | AA37: 0 | AI37: 45872 | AJ37: LLPR | AK37: 0.025 | AL37: 0 | AM37: 152.97
L38: 2119 | M38: Graduate Assistants ERE | N38: 45845 | O38: LLPE | P38: 20250706200001 | Q38: UE | R38: Link Not Available | S38: 45845 | T38: - | U38: - | V38: PAYROLL ENCUMBRANCES | W38: - | X38: - | Y38: 0 | Z38: 0 | AA38: 2129.79 | AI38: 45886 | AJ38: LLPR | AK38: 0.025 | AL38: 0 | AM38: 152.96
N39: 45854 | O39: LLPE | P39: 20250716200001 | Q39: MF | R39: Link Not Available | S39: 45854 | T39: - | U39: - | V39: PAYROLL ENCUMBRANCES | W39: - | X39: - | Y39: 0 | Z39: 0 | AA39: -34.32 | AG39: 2119 Total | AL39: 0 | AM39: 514.98
O40: LLPR | P40: 20250711100002 | Q40: UE | R40: Link Not Available | S40: 45854 | T40: - | U40: 01 | V40: NORMAL PAYROLL ACTIVITY | W40: - | X40: - | Y40: 0 | Z40: 88.47 | AA40: 0 | AG40: 2120 | AH40: Graduate Assistants Tuition Remission ER | AI40: 45844 | AJ40: LLPR | AK40: 0.025 | AL40: 0 | AM40: 0
N41: 45861 | O41: LLPE | P41: 20250723200001 | Q41: MF | R41: Link Not Available | S41: 45861 | T41: - | U41: - | V41: PAYROLL ENCUMBRANCES | W41: - | X41: - | Y41: 0 | Z41: 0 | AA41: -86.19 | AI41: 45858 | AJ41: LLPR | AK41: 0.025 | AL41: 0 | AM41: 0
O42: LLPR | P42: 20250725100001 | Q42: UE | R42: Link Not Available | S42: 45861 | T42: - | U42: 01 | V42: NORMAL PAYROLL ACTIVITY | W42: - | X42: - | Y42: 0 | Z42: 233.9 | AA42: 0 | AI42: 45872 | AJ42: LLPR | AK42: 0.025 | AL42: 0 | AM42: 0
N43: 45875 | O43: LLPE | P43: 20250806200001 | Q43: MF | R43: Link Not Available | S43: 45875 | T43: - | U43: - | V43: PAYROLL ENCUMBRANCES | W43: - | X43: - | Y43: 0 | Z43: 0 | AA43: -85.93 | AI43: 45886 | AJ43: LLPR | AK43: 0.025 | AL43: 0 | AM43: 0
O44: LLPR | P44: 20250808100001 | Q44: UE | R44: Link Not Available | S44: 45875 | T44: - | U44: 01 | V44: NORMAL PAYROLL ACTIVITY | W44: - | X44: - | Y44: 0 | Z44: 210.52 | AA44: 0 | AG44: 2120 Total | AL44: 0 | AM44: 0
U45: 02 | V45: NORMAL PAYROLL ACTIVITY | W45: - | X45: - | Y45: 0 | Z45: 23.39 | AA45: 0 | AD45: - Total | AL45: 335.34 | AM45: 20879.09
N46: 45889 | O46: LLPE | P46: 20250820200000 | Q46: MF | R46: Link Not Available | S46: 45889 | T46: - | U46: - | V46: PAYROLL ENCUMBRANCES | W46: - | X46: - | Y46: 0 | Z46: 0 | AA46: -5.07 | AC46: 1101935 Total | AL46: 335.34 | AM46: 20879.09
P47: 20250820200001 | Q47: MF | R47: Link Not Available | S47: 45889 | T47: - | U47: - | V47: PAYROLL ENCUMBRANCES | W47: - | X47: - | Y47: 0 | Z47: 0 | AA47: -80.99 | AC47: Grand Total | AL47: 335.34 | AM47: 20879.09
O48: LLPR | P48: 20250822100001 | Q48: UE | R48: Link Not Available | S48: 45889 | T48: - | U48: 02 | V48: NORMAL PAYROLL ACTIVITY | W48: - | X48: - | Y48: 0 | Z48: 233.9 | AA48: 0
L49: 2119 Total | Y49: 0 | Z49: 790.18 | AA49: 1837.29
L50: 2121 | M50: Employee Full-Benefit ERE | N50: 45845 | O50: LLPE | P50: 20250706200001 | Q50: UE | R50: Link Not Available | S50: 45845 | T50: - | U50: - | V50: PAYROLL ENCUMBRANCES | W50: - | X50: - | Y50: 0 | Z50: 0 | AA50: 175.04
N51: 45854 | O51: LLPE | P51: 20250716200001 | Q51: MF | R51: Link Not Available | S51: 45854 | T51: - | U51: - | V51: PAYROLL ENCUMBRANCES | W51: - | X51: - | Y51: 0 | Z51: 0 | AA51: -20.8
O52: LLPR | P52: 20250711100002 | Q52: UE | R52: Link Not Available | S52: 45854 | T52: - | U52: 01 | V52: NORMAL PAYROLL ACTIVITY | W52: - | X52: - | Y52: 0 | Z52: 617.55 | AA52: 0
N53: 45861 | O53: LLPE | P53: 20250723200001 | Q53: MF | R53: Link Not Available | S53: 45861 | T53: - | U53: - | V53: PAYROLL ENCUMBRANCES | W53: - | X53: - | Y53: 0 | Z53: 0 | AA53: -51.2
O54: LLPR | P54: 20250725100001 | Q54: UE | R54: Link Not Available | S54: 45861 | T54: - | U54: 01 | V54: NORMAL PAYROLL ACTIVITY | W54: - | X54: - | Y54: 0 | Z54: 1029.24 | AA54: 0
N55: 45875 | O55: LLPE | P55: 20250806200001 | Q55: MF | R55: Link Not Available | S55: 45875 | T55: - | U55: - | V55: PAYROLL ENCUMBRANCES | W55: - | X55: - | Y55: 0 | Z55: 0 | AA55: -51.52
O56: LLPR | P56: 20250808100001 | Q56: UE | R56: Link Not Available | S56: 45875 | T56: - | U56: 01 | V56: NORMAL PAYROLL ACTIVITY | W56: - | X56: - | Y56: 0 | Z56: 926.32 | AA56: 0
U57: 02 | V57: NORMAL PAYROLL ACTIVITY | W57: - | X57: - | Y57: 0 | Z57: 102.92 | AA57: 0
N58: 45889 | O58: LLPE | P58: 20250820200000 | Q58: MF | R58: Link Not Available | S58: 45889 | T58: - | U58: - | V58: PAYROLL ENCUMBRANCES | W58: - | X58: - | Y58: 0 | Z58: 0 | AA58: -51.52
O59: LLPR | P59: 20250822100001 | Q59: UE | R59: Link Not Available | S59: 45889 | T59: - | U59: 02 | V59: NORMAL PAYROLL ACTIVITY | W59: - | X59: - | Y59: 0 | Z59: 720.47 | AA59: 0
L60: 2121 Total | Y60: 0 | Z60: 3396.5 | AA60: -2.8421709e-14
L61: 3870 | M61: Express Shipping | N61: 45889 | O61: PCDO | P61: 31803922 | Q61: 01 | R61: View Document | S61: 45889 | T61: - | U61: - | V61: Shipping Nikon Microscope Stage for repa | W61: Procurement Card - 5745 / MCGHEE, ALEXANDER / 260148 / THE UPS STORE 5220 / $868.34 | X61: - | Y61: 0 | Z61: 868.34 | AA61: 0
L62: 3870 Total | Y62: 0 | Z62: 868.34 | AA62: 0
L63: 4620 | M63: Software Licenses/Royalties | N63: 45868 | O63: PCDO | P63: 31683487 | Q63: 01 | R63: View Document | S63: 45868 | T63: - | U63: - | V63: Paperpile Software July 2025-July 2026 | W63: Procurement Card - 5745 / MCGHEE, ALEXANDER / 254126 / PAPERPILE.COM / $179.40 | X63: - | Y63: 0 | Z63: 179.4 | AA63: 0
L64: 4620 Total | Y64: 0 | Z64: 179.4 | AA64: 0
L65: 5290 | M65: Research Supplies/Medical - Laboratory | N65: 45849 | O65: PO | P65: 31549297 | Q65: 01 | R65: View Document | S65: 45849 | T65: 813479 | U65: - | V65: VWR INTL LLC | W65: PO: 813479 Contract Manager: 99 Vendor: VWR INTL LLC Amount: 89.97 | X65: VWR INTL LLC | Y65: 0 | Z65: 0 | AA65: 89.97
N66: 45862 | O66: PRNC | P66: 31665015 | Q66: 01 | R66: View Document | S66: 45862 | T66: 813479 | U66: 31609346 | V66: VWR INTL LLC | W66: PO: 813479 Vendor: VWR INTL LLC Account: UA 1101935 Amount: 97.26 Pay Date: 08/12/2025 | X66: VWR INTL LLC | Y66: 0 | Z66: 97.26 | AA66: -89.97
N67: 45863 | O67: PRNC | P67: 31681612 | Q67: 01 | R67: View Document | S67: 45863 | T67: 811823 | U67: - | V67: STORES STOCKROOM | W67: PO: 811823 Vendor: STORES STOCKROOM Account: UA 1101935 Amount: 22.26 Pay Date: 07/31/2025 | X67: STORES STOCKROOM | Y67: 0 | Z67: 22.26 | AA67: -22.26
N68: 45868 | O68: PCDO | P68: 31671382 | Q68: 01 | R68: View Document | S68: 45868 | T68: - | U68: - | V68: Pololu-Research supplies for lab | W68: Procurement Card - 5745 / MCGHEE, ALEXANDER / 253493 / POLOLU CORPORATION / $179.19 | X68: - | Y68: 0 | Z68: 179.19 | AA68: 0
N69: 45869 | O69: PO | P69: 770300 | Q69: 01 | R69: View Document | S69: 45853 | T69: 770300 | U69: - | V69: VWR INTL LLC | W69: Procurement Card - 3480 / HALL, ANDREW / 1599607 / PAPA JOHNS #1679 / $117.00 | X69: - | Y69: 0 | Z69: 0 | AA69: 166.88
P70: 788137 | Q70: 01 | R70: View Document | S70: 45853 | T70: 788137 | U70: - | V70: VWR INTL LLC | W70: PO: 9629 Vendor: FEDEX KINKOS Amount: 256.48 | X70: FEDEX KINKOS | Y70: 0 | Z70: 0 | AA70: 91.78
P71: 811823 | Q71: 01 | R71: View Document | S71: 45853 | T71: 811823 | U71: - | V71: STORES STOCKROOM | W71: Edit VendorDetail - Add DBA | X71: - | Y71: 0 | Z71: 0 | AA71: 22.26
N72: 45874 | O72: PCDO | P72: 31683486 | Q72: 01 | R72: View Document | S72: 45874 | T72: - | U72: - | V72: 3D Printing Filament and LEDs | W72: Procurement Card - 5745 / MCGHEE, ALEXANDER / 254164 / AMAZON MKTPL TI8IY4753 / $233.85 | X72: - | Y72: 0 | Z72: 233.85 | AA72: 0
P73: 31683488 | Q73: 01 | R73: View Document | S73: 45874 | T73: - | U73: - | V73: Fans - Culture Cell Experiments | W73: Procurement Card - 5745 / MCGHEE, ALEXANDER / 254024 / AMAZON MKTPL VZ4EB8EZ3 / $10.34 | X73: - | Y73: 0 | Z73: 10.34 | AA73: 0
P74: 31685355 | Q74: 01 | R74: View Document | S74: 45874 | T74: - | U74: - | V74: Cell Culture Experiment-Research Supply | W74: Procurement Card - 5745 / MCGHEE, ALEXANDER / 255087 / AMAZON MKTPL LE73N8XP3 / $410.90 | X74: - | Y74: 0 | Z74: 410.9 | AA74: 0
N75: 45889 | O75: PCDO | P75: 31839338 | Q75: 01 | R75: View Document | S75: 45889 | T75: - | U75: - | V75: Components, motors for BME McGhee Lab | W75: Procurement Card - 5745 / MCGHEE, ALEXANDER / 261891 / AMAZON MKTPL LL0ZG3BQ3 / $44.56 | X75: - | Y75: 0 | Z75: 44.56 | AA75: 0
P76: 31839339 | Q76: 01 | R76: View Document | S76: 45889 | T76: - | U76: - | V76: Components, motors for BME McGhee Lab | W76: Procurement Card - 5745 / MCGHEE, ALEXANDER / 261491 / AMAZON MKTPL 8K9449TH3 / $69.75 | X76: - | Y76: 0 | Z76: 69.75 | AA76: 0
P77: 31839340 | Q77: 01 | R77: View Document | S77: 45889 | T77: - | U77: - | V77: 6x Micro Stepper Motors | W77: Procurement Card - 5745 / MCGHEE, ALEXANDER / 261447 / AMAZON MKTPL IH18O2263 / $110.02 | X77: - | Y77: 0 | Z77: 97.2 | AA77: 0
V78: GT2 Timing Belt | W78: Procurement Card - 5745 / MCGHEE, ALEXANDER / 261447 / AMAZON MKTPL IH18O2263 / $110.02 | X78: - | Y78: 0 | Z78: 12.82 | AA78: 0
P79: 31852037 | Q79: 01 | R79: View Document | S79: 45889 | T79: - | U79: - | V79: Stepper motor, Linear Screw Nut Slider | W79: Procurement Card - 3230 / MCGHEE, ALEXANDER / 262552 / AMAZON MKTPL 3U6WX6II3 / $38.68 | X79: - | Y79: 0 | Z79: 38.68 | AA79: 0
P80: 31865411 | Q80: 01 | R80: View Document | S80: 45889 | T80: - | U80: - | V80: Components, motors for BME McGhee Lab | W80: Procurement Card - 3230 / MCGHEE, ALEXANDER / 262743 / AMAZON MKTPL JP0QJ5ZC3 / $128.63 | X80: - | Y80: 0 | Z80: 128.63 | AA80: 0
P81: 31905311 | Q81: 01 | R81: View Document | S81: 45889 | T81: - | U81: - | V81: Stepper motors for McGheeLab BME | W81: Procurement Card - 3230 / MCGHEE, ALEXANDER / 265472 / AMAZON MKTPL 5504I62G3 / $205.84 | X81: - | Y81: 0 | Z81: 205.84 | AA81: 0
L82: 5290 Total | Y82: 0 | Z82: 1551.28 | AA82: 258.66
L83: 6240 | M83: TRAVEL-OUT STATE | N83: 45849 | O83: DVCA | P83: 31467938 | Q83: 01 | R83: View Document | S83: 45849 | T83: - | U83: 67F9 | V83: Mileage | W83: Disbursement Voucher T - Travel Expense - Alexander McGhee-Colorado [E:N] | X83: - | Y83: 0 | Z83: 799.98 | AA83: 0
L84: 6240 Total | Y84: 0 | Z84: 799.98 | AA84: 0

Sheet 5406011 FY24
B2: INCOME AND EXPENSE REPORT | L2: TRANSACTION REPORT
B4: Account Number | C4: Consolidation Object Name | D4: Object Code | E4: Object Code Name | F4: Current Budget | G4: Fiscal Year Actuals | H4: Inception to Date | I4: Open Encumbrances | J4: Balance Available | L4: Object Code | M4: Object Code Name | N4: Transaction Date | O4: Document | P4: Document Number | Q4: Origin | R4: e-Doc Link | S4: Post Date | T4: Reference Document Number | U4: Organization Document Number | V4: Entry | W4: Document Description | X4: Vendor Name | Y4: Current Budget Amount | Z4: Current Month Actuals | AA4: Encumbrance Amount
B5: 5406011 | C5: OTHER REVENUE | D5: 0360 | E5: Gifts - U of A Foundation | F5: 0 | G5: -20000 | H5: -20000 | I5: 0 | J5: 20000 | L5: 0360 | M5: Gifts - U of A Foundation | N5: 45447 | O5: DI | P5: 28029356 | Q5: 01 | R5: View Document | S5: 45447 | T5: - | U5: TR060324 | V5: 20103408 | W5: Distribution Of Income And Expense - Electronic Payment Claim | X5: - | Y5: 0 | Z5: -20000 | AA5: 0
D6: 0899 | E6: Net Revenues - FSO Only | F6: 0 | G6: 0 | H6: 0 | I6: 0 | J6: 0 | L6: 0360 Total | Y6: 0 | Z6: -20000 | AA6: 0
C7: INCOME Total | F7: 0 | G7: -20000 | H7: -20000 | I7: 0 | J7: 20000 | L7: 7690 | M7: Scientific Equipment | N7: 45380 | O7: PO | P7: 27375160 | Q7: 01 | R7: View Document | S7: 45380 | T7: 749517 | U7: - | V7: NIKON INSTRUMENTS INC | W7: Purchase Order - Alexander McGhee - Nikon | X7: NIKON INSTRUMENTS INC | Y7: 0 | Z7: 0 | AA7: 20000
C8: GENERAL EXPENSES | D8: 5899 | E8: Net Expenses - FSO Only | F8: 0 | G8: 0 | H8: 0 | I8: 0 | J8: 0 | N8: 45449 | O8: PRNC | P8: 28062536 | Q8: 01 | R8: View Document | S8: 45449 | T8: 749517 | U8: - | V8: NIKON INSTRUMENTS INC | W8: PO: 749517 Vendor: NIKON INSTRUMENTS INC Account: UA 1101935 Amount: 540233.87 Pay Date: 06/19/2024 | X8: NIKON INSTRUMENTS INC | Y8: 0 | Z8: 20000.18 | AA8: -20000
C9: CAPITAL | D9: 7690 | E9: Scientific Equipment | F9: 0 | G9: 20000.18 | H9: 20000.18 | I9: 0 | J9: -20000.18 | L9: 7690 Total | Y9: 0 | Z9: 20000.18 | AA9: 0
C10: EXPENSES Total | F10: 0 | G10: 20000.18 | H10: 20000.18 | I10: 0 | J10: -20000.18
B11: Grand Total | F11: 0 | G11: 0.18 | H11: 0.18 | I11: 0 | J11: -0.18

Sheet 2176351 FY25
B2: INCOME AND EXPENSE REPORT | L2: TRANSACTION REPORT
B4: Account Number | C4: Consolidation Object Name | D4: Object Code | E4: Object Code Name | F4: Current Budget | G4: Fiscal Year Actuals | H4: Inception to Date | I4: Open Encumbrances | J4: Balance Available | L4: Object Code | M4: Object Code Name | N4: Transaction Date | O4: Document | P4: Document Number | Q4: Origin | R4: e-Doc Link | S4: Post Date | T4: Reference Document Number | U4: Organization Document Number | V4: Entry | W4: Document Description | X4: Vendor Name | Y4: Current Budget Amount | Z4: Current Month Actuals | AA4: Encumbrance Amount
B5: 2176351 | C5: GENERAL EXPENSES | D5: 4210 | E5: Miscellaneous Research Services | F5: 0 | G5: 1938.36 | H5: 1938.36 | I5: 0 | J5: -1938.36 | L5: 4210 | M5: Miscellaneous Research Services | N5: 45524 | O5: IB | P5: 20240820IL0 | Q5: AR | R5: Link Not Available | S5: 45524 | T5: - | U5: C-4621745 | V5: Alexander McGhee for PI Alexander McGhee | W5: - | X5: - | Y5: 0 | Z5: 20.58 | AA5: 0
D6: 4690 | E6: Rentals - Other | F6: 0 | G6: 423.18 | H6: 423.18 | I6: 0 | J6: -423.18 | N6: 45532 | O6: IB | P6: 20240828IL0 | Q6: CC | R6: Link Not Available | S6: 45532 | T6: - | U6: M-4640808 | V6: Alexander McGhee for PI Alexander McGhee | W6: - | X6: - | Y6: 0 | Z6: 45.5 | AA6: 0
D7: 5290 | E7: Research Supplies/Medical - Laboratory | F7: 0 | G7: 923.33 | H7: 923.33 | I7: 0 | J7: -923.33 | N7: 45561 | O7: IB | P7: 20240926IL0 | Q7: CC | R7: Link Not Available | S7: 45561 | T7: - | U7: E-4699543 | V7: Alia Rose Starman for PI Alexander McGhe | W7: - | X7: - | Y7: 0 | Z7: 521.08 | AA7: 0
D8: 5899 | E8: Net Expenses - FSO Only | F8: 0 | G8: 0 | H8: 0 | I8: 0 | J8: 0 | N8: 45587 | O8: IB | P8: 20241022IL0 | Q8: AR | R8: Link Not Available | S8: 45587 | T8: - | U8: C-4741506 | V8: Alexander McGhee for PI Alexander McGhee | W8: - | X8: - | Y8: 0 | Z8: 13.72 | AA8: 0
C9: EXPENSES Total | F9: 0 | G9: 3284.87 | H9: 3284.87 | I9: 0 | J9: -3284.87 | N9: 45595 | O9: IB | P9: 20241030IL0 | Q9: CC | R9: Link Not Available | S9: 45597 | T9: - | U9: E-4763206 | V9: Alia Rose Starman for PI Alexander McGhe | W9: - | X9: - | Y9: 0 | Z9: 26.03 | AA9: 0
B10: Grand Total | F10: 0 | G10: 3284.87 | H10: 3284.87 | I10: 0 | J10: -3284.87 | N10: 45622 | O10: IB | P10: 20241126IL0 | Q10: CC | R10: Link Not Available | S10: 45622 | T10: - | U10: B-4820552 | V10: Alexander McGhee for PI Alexander McGhee | W10: - | X10: - | Y10: 0 | Z10: 187 | AA10: 0
U11: E-4821580 | V11: Alexander McGhee for PI Alexander McGhee | W11: - | X11: - | Y11: 0 | Z11: 56.43 | AA11: 0
N12: 45708 | O12: IB | P12: 20250220IL0 | Q12: AR | R12: Link Not Available | S12: 45708 | T12: - | U12: C-4971584 | V12: Alexander McGhee for PI Alexander McGhee | W12: - | X12: - | Y12: 0 | Z12: 6.86 | AA12: 0
N13: 45772 | O13: IB | P13: 20250425IL0 | Q13: AR | R13: Link Not Available | S13: 45772 | T13: - | U13: C-5096661 | V13: Alexander McGhee for PI Alexander McGhee | W13: - | X13: - | Y13: 0 | Z13: 6.86 | AA13: 0
N14: 45775 | O14: IB | P14: 20250428IL0 | Q14: CC | R14: Link Not Available | S14: 45775 | T14: - | U14: E-5111826 | V14: Alia Rose Starman for PI Alexander McGhe | W14: - | X14: - | Y14: 0 | Z14: 43.3 | AA14: 0
N15: 45806 | O15: IB | P15: 20250529IL0 | Q15: CC | R15: Link Not Available | S15: 45806 | T15: - | U15: E-5177166 | V15: Alia Rose Starman for PI Alexander McGhe | W15: - | X15: - | Y15: 0 | Z15: 55.9 | AA15: 0
N16: 45826 | O16: IB | P16: 20250618IL0 | Q16: AR | R16: Link Not Available | S16: 45826 | T16: - | U16: C-5220325 | V16: Alexander McGhee for PI Alexander McGhee | W16: - | X16: - | Y16: 0 | Z16: 6.86 | AA16: 0
N17: 45838 | O17: IB | P17: 20250630IL0 | Q17: CC | R17: Link Not Available | S17: 45838 | T17: - | U17: E-5237977 | V17: Alia Rose Starman for PI Alexander McGhe | W17: - | X17: - | Y17: 0 | Z17: 28.26 | AA17: 0
U18: E-5260022 | V18: Alia Rose Starman for PI Alexander McGhe | W18: - | X18: - | Y18: 0 | Z18: 913.12 | AA18: 0
N19: 45841 | O19: IB | P19: 20250703IL0 | Q19: AR | R19: Link Not Available | S19: 45841 | T19: - | U19: C-5269553 | V19: Alexander McGhee for PI Alexander McGhee | W19: - | X19: - | Y19: 0 | Z19: 6.86 | AA19: 0
L20: 4210 Total | Y20: 0 | Z20: 1938.36 | AA20: 0
L21: 4690 | M21: Rentals - Other | N21: 45524 | O21: IB | P21: 20240820IL0 | Q21: AR | R21: Link Not Available | S21: 45524 | T21: - | U21: C-4621745 | V21: Alexander McGhee for PI Alexander McGhee | W21: - | X21: - | Y21: 0 | Z21: 8.64 | AA21: 0
N22: 45560 | O22: IB | P22: 20240925IL0 | Q22: AR | R22: Link Not Available | S22: 45560 | T22: - | U22: C-4688604 | V22: Alexander McGhee for PI Alexander McGhee | W22: - | X22: - | Y22: 0 | Z22: 33.48 | AA22: 0
N23: 45587 | O23: IB | P23: 20241022IL0 | Q23: AR | R23: Link Not Available | S23: 45587 | T23: - | U23: C-4741506 | V23: Alexander McGhee for PI Alexander McGhee | W23: - | X23: - | Y23: 0 | Z23: 37.08 | AA23: 0
N24: 45614 | O24: IB | P24: 20241118IL0 | Q24: AR | R24: Link Not Available | S24: 45614 | T24: - | U24: C-4800990 | V24: Alexander McGhee for PI Alexander McGhee | W24: - | X24: - | Y24: 0 | Z24: 39.06 | AA24: 0
N25: 45659 | O25: IB | P25: 20250102IL0 | Q25: AR | R25: Link Not Available | S25: 45659 | T25: - | U25: C-4857749 | V25: Alexander McGhee for PI Alexander McGhee | W25: - | X25: - | Y25: 0 | Z25: 37.8 | AA25: 0
N26: 45680 | O26: IB | P26: 20250123IL0 | Q26: AR | R26: Link Not Available | S26: 45680 | T26: - | U26: C-4911040 | V26: Alexander McGhee for PI Alexander McGhee | W26: - | X26: - | Y26: 0 | Z26: 39.06 | AA26: 0
N27: 45708 | O27: IB | P27: 20250220IL0 | Q27: AR | R27: Link Not Available | S27: 45708 | T27: - | U27: C-4971584 | V27: Alexander McGhee for PI Alexander McGhee | W27: - | X27: - | Y27: 0 | Z27: 39.06 | AA27: 0
N28: 45743 | O28: IB | P28: 20250327IL0 | Q28: AR | R28: Link Not Available | S28: 45743 | T28: - | U28: C-5032274 | V28: Alexander McGhee for PI Alexander McGhee | W28: - | X28: - | Y28: 0 | Z28: 35.28 | AA28: 0
N29: 45772 | O29: IB | P29: 20250425IL0 | Q29: AR | R29: Link Not Available | S29: 45772 | T29: - | U29: C-5096661 | V29: Alexander McGhee for PI Alexander McGhee | W29: - | X29: - | Y29: 0 | Z29: 39.06 | AA29: 0
N30: 45796 | O30: IB | P30: 20250519IL0 | Q30: AR | R30: Link Not Available | S30: 45796 | T30: - | U30: C-5152019 | V30: Alexander McGhee for PI Alexander McGhee | W30: - | X30: - | Y30: 0 | Z30: 37.8 | AA30: 0
N31: 45826 | O31: IB | P31: 20250618IL0 | Q31: AR | R31: Link Not Available | S31: 45826 | T31: - | U31: C-5220325 | V31: Alexander McGhee for PI Alexander McGhee | W31: - | X31: - | Y31: 0 | Z31: 39.06 | AA31: 0
N32: 45841 | O32: IB | P32: 20250703IL0 | Q32: AR | R32: Link Not Available | S32: 45841 | T32: - | U32: C-5269553 | V32: Alexander McGhee for PI Alexander McGhee | W32: - | X32: - | Y32: 0 | Z32: 37.8 | AA32: 0
L33: 4690 Total | Y33: 0 | Z33: 423.18 | AA33: 0
L34: 5290 | M34: Research Supplies/Medical - Laboratory | N34: 45524 | O34: IB | P34: 20240820IL0 | Q34: AR | R34: Link Not Available | S34: 45524 | T34: - | U34: C-4621745 | V34: Alexander McGhee for PI Alexander McGhee | W34: - | X34: - | Y34: 0 | Z34: 116.14 | AA34: 0
N35: 45587 | O35: IB | P35: 20241022IL0 | Q35: AR | R35: Link Not Available | S35: 45587 | T35: - | U35: C-4741506 | V35: Alexander McGhee for PI Alexander McGhee | W35: - | X35: - | Y35: 0 | Z35: 506.48 | AA35: 0
N36: 45708 | O36: IB | P36: 20250220IL0 | Q36: AR | R36: Link Not Available | S36: 45708 | T36: - | U36: C-4971584 | V36: Alexander McGhee for PI Alexander McGhee | W36: - | X36: - | Y36: 0 | Z36: 11.56 | AA36: 0
N37: 45772 | O37: IB | P37: 20250425IL0 | Q37: AR | R37: Link Not Available | S37: 45772 | T37: - | U37: C-5096661 | V37: Alexander McGhee for PI Alexander McGhee | W37: - | X37: - | Y37: 0 | Z37: 11.56 | AA37: 0
N38: 45826 | O38: IB | P38: 20250618IL0 | Q38: AR | R38: Link Not Available | S38: 45826 | T38: - | U38: C-5220325 | V38: Alexander McGhee for PI Alexander McGhee | W38: - | X38: - | Y38: 0 | Z38: 24.35 | AA38: 0
N39: 45841 | O39: IB | P39: 20250703IL0 | Q39: AR | R39: Link Not Available | S39: 45841 | T39: - | U39: C-5269553 | V39: Alexander McGhee for PI Alexander McGhee | W39: - | X39: - | Y39: 0 | Z39: 253.24 | AA39: 0
L40: 5290 Total | Y40: 0 | Z40: 923.33 | AA40: 0

Sheet 2176351 FY26
B2: INCOME AND EXPENSE REPORT | L2: TRANSACTION REPORT
B4: Account Number | C4: Consolidation Object Name | D4: Object Code | E4: Object Code Name | F4: Current Budget | G4: Fiscal Year Actuals | H4: Inception to Date | I4: Open Encumbrances | J4: Balance Available | L4: Object Code | M4: Object Code Name | N4: Transaction Date | O4: Document | P4: Document Number | Q4: Origin | R4: e-Doc Link | S4: Post Date | T4: Reference Document Number | U4: Organization Document Number | V4: Entry | W4: Document Description | X4: Vendor Name | Y4: Current Budget Amount | Z4: Current Month Actuals | AA4: Encumbrance Amount
B5: 2176351 | C5: GENERAL EXPENSES | D5: 4210 | E5: Miscellaneous Research Services | F5: 0 | G5: 13.72 | H5: 13.72 | I5: 0 | J5: -13.72 | L5: 4210 | M5: Miscellaneous Research Services | N5: 45888 | O5: IB | P5: 20250819IL0 | Q5: AR | R5: Link Not Available | S5: 45888 | T5: - | U5: C-5346987 | V5: Alexander McGhee for PI Alexander McGhee | W5: - | X5: - | Y5: 0 | Z5: 6.86 | AA5: 0
D6: 4690 | E6: Rentals - Other | F6: 0 | G6: 39.06 | H6: 39.06 | I6: 0 | J6: -39.06 | V6: Alia Rose Starman for PI Alexander McGhe | W6: - | X6: - | Y6: 0 | Z6: 6.86 | AA6: 0
D7: 5290 | E7: Research Supplies/Medical - Laboratory | F7: 0 | G7: 277.59 | H7: 277.59 | I7: 0 | J7: -277.59 | L7: 4210 Total | Y7: 0 | Z7: 13.72 | AA7: 0
C8: EXPENSES Total | F8: 0 | G8: 330.37 | H8: 330.37 | I8: 0 | J8: -330.37 | L8: 4690 | M8: Rentals - Other | N8: 45888 | O8: IB | P8: 20250819IL0 | Q8: AR | R8: Link Not Available | S8: 45888 | T8: - | U8: C-5346987 | V8: Alexander McGhee for PI Alexander McGhee | W8: - | X8: - | Y8: 0 | Z8: 39.06 | AA8: 0
B9: Grand Total | F9: 0 | G9: 330.37 | H9: 330.37 | I9: 0 | J9: -330.37 | L9: 4690 Total | Y9: 0 | Z9: 39.06 | AA9: 0
L10: 5290 | M10: Research Supplies/Medical - Laboratory | N10: 45888 | O10: IB | P10: 20250819IL0 | Q10: AR | R10: Link Not Available | S10: 45888 | T10: - | U10: C-5346987 | V10: Alexander McGhee for PI Alexander McGhee | W10: - | X10: - | Y10: 0 | Z10: 253.24 | AA10: 0
V11: Alia Rose Starman for PI Alexander McGhe | W11: - | X11: - | Y11: 0 | Z11: 24.35 | AA11: 0
L12: 5290 Total | Y12: 0 | Z12: 277.59 | AA12: 0

Sheet 2176300 BMEAM FY24
B2: INCOME AND EXPENSE REPORT | L2: TRANSACTION REPORT
B4: Account Number | C4: Consolidation Object Name | D4: Object Code | E4: Object Code Name | F4: Current Budget | G4: Fiscal Year Actuals | H4: Inception to Date | I4: Open Encumbrances | J4: Balance Available | L4: Object Code | M4: Object Code Name | N4: Transaction Date | O4: Document | P4: Document Number | Q4: Origin | R4: e-Doc Link | S4: Post Date | T4: Reference Document Number | U4: Organization Document Number | V4: Entry | W4: Document Description | X4: Vendor Name | Y4: Current Budget Amount | Z4: Current Month Actuals | AA4: Encumbrance Amount
B5: 2176300-BMEAM | C5: GENERAL EXPENSES | D5: 5490 | E5: Operating Supplies - Other | F5: 0 | G5: 181.09 | H5: 181.09 | I5: 0 | J5: -181.09 | L5: 5490 | M5: Operating Supplies - Other | N5: 45469 | O5: PCDO | P5: 28155297 | Q5: 01 | R5: View Document | S5: 45469 | T5: - | U5: - | V5: Wall mount for gas cylinders | W5: Procurement Card - 5745 / MCGHEE, ALEXANDER / 50424 / MCMASTER-CARR / $217.60 | X5: - | Y5: 0 | Z5: 181.09 | AA5: 0
D6: 5560 | E6: Freight In/Out - (Noncapital related) | F6: 0 | G6: 36.51 | H6: 36.51 | I6: 0 | J6: -36.51 | L6: 5490 Total | Y6: 0 | Z6: 181.09 | AA6: 0
D7: 5899 | E7: Net Expenses - FSO Only | F7: 0 | G7: 0 | H7: 0 | I7: 0 | J7: 0 | L7: 5560 | M7: Freight In/Out - (Noncapital related) | N7: 45469 | O7: PCDO | P7: 28155297 | Q7: 01 | R7: View Document | S7: 45469 | T7: - | U7: - | V7: shipping cost | W7: Procurement Card - 5745 / MCGHEE, ALEXANDER / 50424 / MCMASTER-CARR / $217.60 | X7: - | Y7: 0 | Z7: 36.51 | AA7: 0
C8: EXPENSES Total | F8: 0 | G8: 217.6 | H8: 217.6 | I8: 0 | J8: -217.6 | L8: 5560 Total | Y8: 0 | Z8: 36.51 | AA8: 0
B9: GRAND TOTAL | F9: 0 | G9: 217.6 | H9: 217.6 | I9: 0 | J9: -217.6

Sheet 2176300 BMEAM FY25
B2: INCOME AND EXPENSE REPORT | L2: TRANSACTION REPORT
B4: Account Number | C4: Consolidation Object Name | D4: Object Code | E4: Object Code Name | F4: Current Budget | G4: Fiscal Year Actuals | H4: Inception to Date | I4: Open Encumbrances | J4: Balance Available | L4: Object Code | M4: Object Code Name | N4: Transaction Date | O4: Document | P4: Document Number | Q4: Origin | R4: e-Doc Link | S4: Post Date | T4: Reference Document Number | U4: Organization Reference ID | V4: Entry | W4: Document Description | X4: Vendor Name | Y4: Current Budget Amount | Z4: Current Month Actuals | AA4: Encumbrance Amount
B5: 2176300-BMEAM | C5: GENERAL EXPENSES | D5: 3510 | E5: R/M Services-Buildings | F5: 0 | G5: 0 | H5: 0 | I5: 0 | J5: 0 | L5: 3510 | M5: R/M Services-Buildings | N5: 45772 | O5: GEC | P5: 30783481 | Q5: 01 | R5: View Document | S5: 45772 | T5: - | U5: 1664396 | V5: FM-20240926FM1: S5914/John Gaff/need ... | W5: General Error Correction - BME IDC - Main Account Clean Up | X5: - | Y5: 0 | Z5: 29.38 | AA5: 0
D6: 3870 | E6: Express Shipping | F6: 0 | G6: 0 | H6: 0 | I6: 0 | J6: 0 | V6: FM-20241016FM1: S5914/John Gaff/need ... | W6: General Error Correction - BME IDC - Main Account Clean Up | X6: - | Y6: 0 | Z6: 62.5 | AA6: 0
D7: 4620 | E7: Software Licenses/Royalties | F7: 0 | G7: 0 | H7: 0 | I7: 0 | J7: 0 | V7: FM-20241219FM1: S5914/John Gaff/need ... | W7: General Error Correction - BME IDC - Main Account Clean Up | X7: - | Y7: 0 | Z7: 250 | AA7: 0
D8: 5150 | E8: Data Processing Supplies | F8: 0 | G8: 0 | H8: 0 | I8: 0 | J8: 0 | N8: 45849 | O8: YEGE | P8: 31553281 | Q8: 01 | R8: View Document | S8: 45849 | T8: - | U8: 1664396 | V8: 01-30783481: FM-20240926FM1: S5914/Jo... | W8: Year End General Error Correction - Moving expenses to correct account | X8: - | Y8: 0 | Z8: -29.38 | AA8: 0
D9: 5230 | E9: Office Supplies | F9: 0 | G9: 0 | H9: 0 | I9: 0 | J9: 0 | V9: 01-30783481: FM-20241016FM1: S5914/Jo... | W9: Year End General Error Correction - Moving expenses to correct account | X9: - | Y9: 0 | Z9: -62.5 | AA9: 0
D10: 5290 | E10: Research Supplies/Medical - Laboratory | F10: 0 | G10: 0 | H10: 0 | I10: 0 | J10: 0 | V10: 01-30783481: FM-20241219FM1: S5914/Jo... | W10: Year End General Error Correction - Moving expenses to correct account | X10: - | Y10: 0 | Z10: -250 | AA10: 0
D11: 5490 | E11: Operating Supplies - Other | F11: 0 | G11: 0 | H11: 0 | I11: 0 | J11: 0 | L11: 3510 Total | Y11: 0 | Z11: 0 | AA11: 0
D12: 5520 | E12: Conference Registration Fees | F12: 0 | G12: 0 | H12: 0 | I12: 0 | J12: 0 | L12: 3870 | M12: Express Shipping | N12: 45531 | O12: PCDO | P12: 28659256 | Q12: 01 | R12: View Document | S12: 45531 | T12: - | U12: - | V12: Delivery | W12: Procurement Card - 5745 / MCGHEE, ALEXANDER / 76752 / UPS E8K138BGNLD / $95.32 | X12: - | Y12: 0 | Z12: 95.32 | AA12: 0
D13: 5535 | E13: Purchasing Transaction Fees | F13: 0 | G13: 0 | H13: 0 | I13: 0 | J13: 0 | N13: 45849 | O13: YEGE | P13: 31553281 | Q13: 01 | R13: View Document | S13: 45849 | T13: - | U13: - | V13: 01-28659256: Delivery | W13: Year End General Error Correction - Moving expenses to correct account | X13: - | Y13: 0 | Z13: -95.32 | AA13: 0
D14: 5560 | E14: Freight In/Out - (Noncapital related) | F14: 0 | G14: 0 | H14: 0 | I14: 0 | J14: 0 | L14: 3870 Total | Y14: 0 | Z14: 0 | AA14: 0
D15: 5760 | E15: Noncapitalized Equipment - EDP | F15: 0 | G15: 0 | H15: 0 | I15: 0 | J15: 0 | L15: 4620 | M15: Software Licenses/Royalties | N15: 45554 | O15: PCDO | P15: 28849510 | Q15: 01 | R15: View Document | S15: 45554 | T15: - | U15: - | V15: Aid for LaTex code | W15: Procurement Card - Auto Approve 09/19/2024 12:18 AM / 88921 / OVERLEAF SHARELATEX / $200.99 | X15: - | Y15: 0 | Z15: 199 | AA15: 0
D16: 5899 | E16: Net Expenses - FSO Only | F16: 0 | G16: 0 | H16: 0 | I16: 0 | J16: 0 | V16: Use Tax 5.600% on 199.00 | W16: Procurement Card - Auto Approve 09/19/2024 12:18 AM / 88921 / OVERLEAF SHARELATEX / $200.99 | X16: - | Y16: 0 | Z16: 11.14 | AA16: 0
C17: TRAVEL | D17: 6240 | E17: TRAVEL-OUT STATE | F17: 0 | G17: 322.72 | H17: 322.72 | I17: 0 | J17: -322.72 | N17: 45560 | O17: PCDO | P17: 28915583 | Q17: 01 | R17: View Document | S17: 45560 | T17: - | U17: - | V17: Coding development | W17: Procurement Card - 5745 / MCGHEE, ALEXANDER / 91406 / GITHUB, INC. / $100.00 | X17: - | Y17: 0 | Z17: 100 | AA17: 0
D18: 6241 | E18: TRAVEL-OUT OF STATE AIRLINES | F18: 0 | G18: 0 | H18: 0 | I18: 0 | J18: 0 | N18: 45849 | O18: YEGE | P18: 31553281 | Q18: 01 | R18: View Document | S18: 45849 | T18: - | U18: - | V18: 01-28849510: Aid for LaTex code | W18: Year End General Error Correction - Moving expenses to correct account | X18: - | Y18: 0 | Z18: -199 | AA18: 0
D19: 6242 | E19: TRAVEL-OUT STATE HOTEL | F19: 0 | G19: 495 | H19: 495 | I19: 0 | J19: -495 | V19: 01-28849510: Use Tax 5.600% on 199.00 | W19: Year End General Error Correction - Moving expenses to correct account | X19: - | Y19: 0 | Z19: -11.14 | AA19: 0
C20: CAPITAL | D20: 7690 | E20: Scientific Equipment | F20: 0 | G20: 23253.64 | H20: 23253.64 | I20: 0 | J20: -23253.64 | V20: 01-28915583: Coding development | W20: Year End General Error Correction - Moving expenses to correct account | X20: - | Y20: 0 | Z20: -100 | AA20: 0
C21: EXPENSES Total | F21: 0 | G21: 24071.36 | H21: 24071.36 | I21: 0 | J21: -24071.36 | L21: 4620 Total | Y21: 0 | Z21: -1.4210855e-14 | AA21: 0
B22: GRAND TOTAL | F22: 0 | G22: 24071.36 | H22: 24071.36 | I22: 0 | J22: -24071.36 | L22: 5150 | M22: Data Processing Supplies | N22: 45762 | O22: PCDO | P22: 30637468 | Q22: 01 | R22: View Document | S22: 45762 | T22: - | U22: - | V22: WIFI Adapter | W22: Procurement Card - 5745 / MCGHEE, ALEXANDER / 195965 / Amazon.com 9V87N4HZ3 / $102.69 | X22: - | Y22: 0 | Z22: 102.69 | AA22: 0
N23: 45849 | O23: YEGE | P23: 31553281 | Q23: 01 | R23: View Document | S23: 45849 | T23: - | U23: - | V23: 01-30637468: WIFI Adapter | W23: Year End General Error Correction - Moving expenses to correct account | X23: - | Y23: 0 | Z23: -102.69 | AA23: 0
L24: 5150 Total | Y24: 0 | Z24: 0 | AA24: 0
L25: 5230 | M25: Office Supplies | N25: 45681 | O25: PCDO | P25: 29862492 | Q25: 01 | R25: View Document | S25: 45681 | T25: - | U25: - | V25: White Board | W25: Procurement Card - 5745 / MCGHEE, ALEXANDER / 147931 / Amazon.com ZD5950EW0 / $163.04 | X25: - | Y25: 0 | Z25: 163.04 | AA25: 0
N26: 45849 | O26: YEGE | P26: 31553281 | Q26: 01 | R26: View Document | S26: 45849 | T26: - | U26: - | V26: 01-29862492: White Board | W26: Year End General Error Correction - Moving expenses to correct account | X26: - | Y26: 0 | Z26: -163.04 | AA26: 0
L27: 5230 Total | Y27: 0 | Z27: 0 | AA27: 0
L28: 5290 | M28: Research Supplies/Medical - Laboratory | N28: 45557 | O28: PCDO | P28: 28885555 | Q28: 01 | R28: View Document | S28: 45558 | T28: - | U28: - | V28: various sized bolts | W28: Procurement Card - Auto Approve 09/22/2024 12:47 AM / 89722 / AMAZON MKTPL ZT3TK73C1 / $19.50 | X28: - | Y28: 0 | Z28: 19.5 | AA28: 0
N29: 45560 | O29: PCDO | P29: 28915581 | Q29: 01 | R29: View Document | S29: 45560 | T29: - | U29: - | V29: Use Tax 5.600% on 510.61 | W29: Procurement Card - 5745 / MCGHEE, ALEXANDER / 92241 / SOUTHERN LABWARE INC / $510.61 | X29: - | Y29: 0 | Z29: 28.59 | AA29: 0
V30: Vactrap XL | W30: Procurement Card - 5745 / MCGHEE, ALEXANDER / 92241 / SOUTHERN LABWARE INC / $510.61 | X30: - | Y30: 0 | Z30: 510.61 | AA30: 0
P31: 28915582 | Q31: 01 | R31: View Document | S31: 45560 | T31: - | U31: - | V31: plastic bins and bottles | W31: Procurement Card - 5745 / MCGHEE, ALEXANDER / 91805 / AMAZON MKTPL ZT0SA1X71 / $38.46 | X31: - | Y31: 0 | Z31: 38.46 | AA31: 0
N32: 45608 | O32: PCDO | P32: 29395323 | Q32: 01 | R32: View Document | S32: 45608 | T32: - | U32: - | V32: Multiple sensors | W32: Procurement Card - 5745 / MCGHEE, ALEXANDER / 121215 / DKC DIGI KEY CORP / $286.74 | X32: - | Y32: 0 | Z32: 281.75 | AA32: 0
N33: 45700 | O33: PCDO | P33: 30015941 | Q33: 01 | R33: View Document | S33: 45700 | T33: - | U33: - | V33: Lab supplies | W33: Procurement Card - 5745 / MCGHEE, ALEXANDER / 156750 / AMAZON MKTPL ZC8BE0IB2 / $65.16 | X33: - | Y33: 0 | Z33: 65.16 | AA33: 0
P34: 30015942 | Q34: 01 | R34: View Document | S34: 45700 | T34: - | U34: - | V34: Lab supplies | W34: Procurement Card - 5745 / MCGHEE, ALEXANDER / 157524 / STEMCULTURES / $797.20 | X34: - | Y34: 0 | Z34: 797.2 | AA34: 0
V35: Use Tax 5.600% on 797.20 | W35: Procurement Card - 5745 / MCGHEE, ALEXANDER / 157524 / STEMCULTURES / $797.20 | X35: - | Y35: 0 | Z35: 44.64 | AA35: 0
N36: 45762 | O36: GEC | P36: 30721084 | Q36: 01 | R36: View Document | S36: 45762 | T36: - | U36: - | V36: 01-30015942: Lab supplies | W36: General Error Correction - Pcard 5745 Alex McGhee | X36: - | Y36: 0 | Z36: -797.2 | AA36: 0
V37: 01-30015942: Use Tax 5.600% on 797.20 | W37: General Error Correction - Pcard 5745 Alex McGhee | X37: - | Y37: 0 | Z37: -44.64 | AA37: 0
N38: 45769 | O38: PCDO | P38: 30637466 | Q38: 01 | R38: View Document | S38: 45769 | T38: - | U38: - | V38: Auto Approve 04/22/2025 12:18 AM | W38: Procurement Card - Auto Approve 04/22/2025 12:18 AM / 196363 / BANGS LABORATORIES / $2404.13 | X38: - | Y38: 0 | Z38: 2404.13 | AA38: 0
V39: Use Tax 5.600% on 2404.13 | W39: Procurement Card - Auto Approve 04/22/2025 12:18 AM / 196363 / BANGS LABORATORIES / $2404.13 | X39: - | Y39: 0 | Z39: 134.63 | AA39: 0
N40: 45804 | O40: GEC | P40: 31099851 | Q40: 01 | R40: View Document | S40: 45804 | T40: - | U40: - | V40: 01-30637466: Auto Approve 04/22/2025 ... | W40: General Error Correction - MCGHEE, ALEXANDER 5745 | X40: - | Y40: 0 | Z40: -2404.13 | AA40: 0
N41: 45819 | O41: GEC | P41: 31240228 | Q41: 01 | R41: View Document | S41: 45819 | T41: - | U41: - | V41: 01-30015941: Lab supplies | W41: General Error Correction - MCGHEE, ALEXANDER 5745 | X41: - | Y41: 0 | Z41: -65.16 | AA41: 0
N42: 45849 | O42: YEGE | P42: 31553281 | Q42: 01 | R42: View Document | S42: 45849 | T42: - | U42: - | V42: 01-28885555: various sized bolts | W42: Year End General Error Correction - Moving expenses to correct account | X42: - | Y42: 0 | Z42: -19.5 | AA42: 0
V43: 01-28915581: Use Tax 5.600% on 510.61 | W43: Year End General Error Correction - Moving expenses to correct account | X43: - | Y43: 0 | Z43: -28.59 | AA43: 0
V44: 01-28915581: Vactrap XL | W44: Year End General Error Correction - Moving expenses to correct account | X44: - | Y44: 0 | Z44: -510.61 | AA44: 0
V45: 01-28915582: plastic bins and bottles | W45: Year End General Error Correction - Moving expenses to correct account | X45: - | Y45: 0 | Z45: -38.46 | AA45: 0
V46: 01-29395323: Multiple sensors | W46: Year End General Error Correction - Moving expenses to correct account | X46: - | Y46: 0 | Z46: -281.75 | AA46: 0
V47: 01-30637466: Use Tax 5.600% on 2404.13 | W47: Year End General Error Correction - Moving expenses to correct account | X47: - | Y47: 0 | Z47: -134.63 | AA47: 0
L48: 5290 Total | Y48: 0 | Z48: 7.3896445e-13 | AA48: 0
L49: 5490 | M49: Operating Supplies - Other | N49: 45560 | O49: PCDO | P49: 28915580 | Q49: 01 | R49: View Document | S49: 45560 | T49: - | U49: - | V49: Eye protection and tape | W49: Procurement Card - 5745 / MCGHEE, ALEXANDER / 92195 / AMAZON MKTPL ZT24R49G2 / $67.55 | X49: - | Y49: 0 | Z49: 67.55 | AA49: 0
N50: 45849 | O50: YEGE | P50: 31553281 | Q50: 01 | R50: View Document | S50: 45849 | T50: - | U50: - | V50: 01-28915580: Eye protection and tape | W50: Year End General Error Correction - Moving expenses to correct account | X50: - | Y50: 0 | Z50: -67.55 | AA50: 0
L51: 5490 Total | Y51: 0 | Z51: 0 | AA51: 0
L52: 5520 | M52: Conference Registration Fees | N52: 45533 | O52: PCDO | P52: 28711057 | Q52: 01 | R52: View Document | S52: 45533 | T52: - | U52: - | V52: Conference Registration Fee to BMES | W52: Procurement Card - 5745 / MCGHEE, ALEXANDER / 80474 / BIOMEDICAL ENGINEERING SO / $625.00 | X52: - | Y52: 0 | Z52: 625 | AA52: 0
N53: 45849 | O53: YEGE | P53: 31553281 | Q53: 01 | R53: View Document | S53: 45849 | T53: - | U53: - | V53: 01-28711057: Conference Registration ... | W53: Year End General Error Correction - Moving expenses to correct account | X53: - | Y53: 0 | Z53: -625 | AA53: 0
L54: 5520 Total | Y54: 0 | Z54: 0 | AA54: 0
L55: 5535 | M55: Purchasing Transaction Fees | N55: 45554 | O55: PCDO | P55: 28849510 | Q55: 01 | R55: View Document | S55: 45554 | T55: - | U55: - | V55: Bank Fee Foreign | W55: Procurement Card - Auto Approve 09/19/2024 12:18 AM / 88921 / OVERLEAF SHARELATEX / $200.99 | X55: - | Y55: 0 | Z55: 1.99 | AA55: 0
N56: 45849 | O56: YEGE | P56: 31553281 | Q56: 01 | R56: View Document | S56: 45849 | T56: - | U56: - | V56: 01-28849510: Bank Fee Foreign | W56: Year End General Error Correction - Moving expenses to correct account | X56: - | Y56: 0 | Z56: -1.99 | AA56: 0
L57: 5535 Total | Y57: 0 | Z57: 0 | AA57: 0
L58: 5560 | M58: Freight In/Out - (Noncapital related) | N58: 45608 | O58: PCDO | P58: 29395323 | Q58: 01 | R58: View Document | S58: 45608 | T58: - | U58: - | V58: Multiple sensors | W58: Procurement Card - 5745 / MCGHEE, ALEXANDER / 121215 / DKC DIGI KEY CORP / $286.74 | X58: - | Y58: 0 | Z58: 4.99 | AA58: 0
N59: 45849 | O59: YEGE | P59: 31553281 | Q59: 01 | R59: View Document | S59: 45849 | T59: - | U59: - | V59: 01-29395323: Multiple sensors | W59: Year End General Error Correction - Moving expenses to correct account | X59: - | Y59: 0 | Z59: -4.99 | AA59: 0
L60: 5560 Total | Y60: 0 | Z60: 0 | AA60: 0
L61: 5760 | M61: Noncapitalized Equipment - EDP | N61: 45588 | O61: PCDO | P61: 29173181 | Q61: 01 | R61: View Document | S61: 45588 | T61: - | U61: - | V61: TV mount | W61: Procurement Card - 5745 / MCGHEE, ALEXANDER / 107222 / AMAZON RETA O962810D3 / $43.47 | X61: - | Y61: 0 | Z61: 43.47 | AA61: 0
P62: 29173182 | Q62: 01 | R62: View Document | S62: 45588 | T62: - | U62: - | V62: cable management | W62: Procurement Card - 5745 / MCGHEE, ALEXANDER / 107764 / AMAZON RETA 7G91K8SD3 / $21.73 | X62: - | Y62: 0 | Z62: 21.73 | AA62: 0
N63: 45762 | O63: PCDO | P63: 30623897 | Q63: 01 | R63: View Document | S63: 45762 | T63: - | U63: - | V63: USB3 Hub | W63: Procurement Card - 5745 / MCGHEE, ALEXANDER / 195697 / AMAZON MKTPL NE1WD2JM3 / $41.28 | X63: - | Y63: 0 | Z63: 41.28 | AA63: 0
P64: 30623899 | Q64: 01 | R64: View Document | S64: 45762 | T64: - | U64: - | V64: USB docking station | W64: Procurement Card - 5745 / MCGHEE, ALEXANDER / 195727 / AMAZON MKTPL CM0IZ4PC3 / $86.94 | X64: - | Y64: 0 | Z64: 86.94 | AA64: 0
P65: 30665061 | Q65: 01 | R65: View Document | S65: 45762 | T65: - | U65: - | V65: Monitors and peripheral devices | W65: Procurement Card - 5745 / MCGHEE, ALEXANDER / 197879 / Amazon.com 5N17C16Y3 / $3956.15 | X65: - | Y65: 0 | Z65: 3956.15 | AA65: 0
N66: 45849 | O66: YEGE | P66: 31553281 | Q66: 01 | R66: View Document | S66: 45849 | T66: - | U66: - | V66: 01-29173181: TV mount | W66: Year End General Error Correction - Moving expenses to correct account | X66: - | Y66: 0 | Z66: -43.47 | AA66: 0
V67: 01-29173182: cable management | W67: Year End General Error Correction - Moving expenses to correct account | X67: - | Y67: 0 | Z67: -21.73 | AA67: 0
V68: 01-30623897: USB3 Hub | W68: Year End General Error Correction - Moving expenses to correct account | X68: - | Y68: 0 | Z68: -41.28 | AA68: 0
V69: 01-30623899: USB docking station | W69: Year End General Error Correction - Moving expenses to correct account | X69: - | Y69: 0 | Z69: -86.94 | AA69: 0
V70: 01-30665061: Monitors and peripheral ... | W70: Year End General Error Correction - Moving expenses to correct account | X70: - | Y70: 0 | Z70: -3956.15 | AA70: 0
L71: 5760 Total | Y71: 0 | Z71: -9.094947e-13 | AA71: 0
L72: 6240 | M72: TRAVEL-OUT STATE | N72: 45484 | O72: DVCA | P72: 28255254 | Q72: 01 | R72: View Document | S72: 45484 | T72: - | U72: - | V72: Meals and Transportation | W72: Disbursement Voucher T - Travel Expense - Alexander McGhee Vancouver WA [E:N] | X72: - | Y72: 0 | Z72: 322.72 | AA72: 0
L73: 6240 Total | Y73: 0 | Z73: 322.72 | AA73: 0
L74: 6241 | M74: TRAVEL-OUT OF STATE AIRLINES | N74: 45808 | O74: PCDO | P74: 30997778 | Q74: 01 | R74: View Document | S74: 45810 | T74: - | U74: - | V74: Auto Approve 05/31/2025 12:22 AM | W74: Procurement Card - Auto Approve 05/31/2025 12:22 AM / 218665 / FRONTIER AI FGCJNT / $179.98 | X74: - | Y74: 0 | Z74: 179.98 | AA74: 0
P75: 30997779 | Q75: 01 | R75: View Document | S75: 45810 | T75: - | U75: - | V75: Auto Approve 05/31/2025 12:22 AM | W75: Procurement Card - Auto Approve 05/31/2025 12:22 AM / 219463 / SOUTHWES 5262343367185 / $264.49 | X75: - | Y75: 0 | Z75: 264.49 | AA75: 0
N76: 45820 | O76: GEC | P76: 31258591 | Q76: 01 | R76: View Document | S76: 45820 | T76: - | U76: - | V76: 01-30997778: Auto Approve 05/31/2025 ... | W76: General Error Correction - MCGHEE, ALEXANDER 5745 | X76: - | Y76: 0 | Z76: -179.98 | AA76: 0
V77: 01-30997779: Auto Approve 05/31/2025 ... | W77: General Error Correction - MCGHEE, ALEXANDER 5745 | X77: - | Y77: 0 | Z77: -264.49 | AA77: 0
L78: 6241 Total | Y78: 0 | Z78: 0 | AA78: 0
L79: 6242 | M79: TRAVEL-OUT STATE HOTEL | N79: 45484 | O79: DVCA | P79: 28255254 | Q79: 01 | R79: View Document | S79: 45484 | T79: - | U79: - | V79: Lodging | W79: Disbursement Voucher T - Travel Expense - Alexander McGhee Vancouver WA [E:N] | X79: - | Y79: 0 | Z79: 495 | AA79: 0
L80: 6242 Total | Y80: 0 | Z80: 495 | AA80: 0
L81: 7690 | M81: Scientific Equipment | N81: 45604 | O81: POA | P81: 28757619 | Q81: 01 | R81: View Document | S81: 45604 | T81: 749517 | U81: - | V81: NIKON INSTRUMENTS INC | W81: PO: 749517 Contract Manager: 39 Vendor: NIKON INSTRUMENTS INC Amount: 562254.36 | X81: NIKON INSTRUMENTS INC | Y81: 0 | Z81: 0 | AA81: 22020.49
N82: 45609 | O82: PRNC | P82: 29474828 | Q82: 01 | R82: View Document | S82: 45609 | T82: 749517 | U82: - | V82: NIKON INSTRUMENTS INC | W82: PO: 749517 Vendor: NIKON INSTRUMENTS INC Account: UA 2176300 BMEAM Amount: 23253.64 Pay Date: 11/13/2024 | X82: NIKON INSTRUMENTS INC | Y82: 0 | Z82: 23253.64 | AA82: -22020.49
L83: 7690 Total | Y83: 0 | Z83: 23253.64 | AA83: 0

Sheet 2215510 BME AM FY24
B2: INCOME AND EXPENSE REPORT | L2: TRANSACTION REPORT
B4: Account Number | C4: Consolidation Object Name | D4: Object Code | E4: Object Code Name | F4: Current Budget | G4: Fiscal Year Actuals | H4: Inception to Date | I4: Open Encumbrances | J4: Balance Available | L4: Object Code | M4: Object Code Name | N4: Transaction Date | O4: Document | P4: Document Number | Q4: Origin | R4: e-Doc Link | S4: Post Date | T4: Reference Document Number | U4: Organization Document Number | V4: Entry | W4: Document Description | X4: Vendor Name | Y4: Current Budget Amount | Z4: Current Month Actuals | AA4: Encumbrance Amount
B5: 2215510-BMEAM | C5: OTHER REVENUE | D5: 0899 | E5: Net Revenues - FSO Only | F5: 0 | G5: 0 | H5: 0 | I5: 0 | J5: 0 | L5: 0930 | M5: Voluntary Transfer In | N5: 45350 | O5: TF | P5: 27123305 | Q5: 01 | R5: View Document | S5: 45350 | T5: - | U5: - | V5: 2215510/2259000 | W5: Transfer Of Funds - 2215510/2259000 | X5: - | Y5: 0 | Z5: -300000 | AA5: 0
C6: TRANSFER OF FUNDS | D6: 0930 | E6: Voluntary Transfer In | F6: 0 | G6: -300000 | H6: -300000 | I6: 0 | J6: 300000 | L6: 0930 Total | Y6: 0 | Z6: -300000 | AA6: 0
D7: 0939 | E7: Transfers In / Allocations | F7: 0 | G7: -0.07 | H7: -0.07 | I7: 0 | J7: 0.07 | L7: 0939 | M7: Transfers In / Allocations | N7: 45481 | O7: YETF | P7: 28358541 | Q7: 01 | R7: View Document | S7: 45481 | T7: - | U7: - | V7: MOVING TO SUB | W7: Year End Transfer Of Funds - CLEARING DEF. to subaccount BMEAM | X7: - | Y7: 0 | Z7: -0.07 | AA7: 0
C8: INCOME Total | F8: 0 | G8: -300000.07 | H8: -300000.07 | I8: 0 | J8: 300000.07 | L8: 0939 Total | Y8: 0 | Z8: -0.07 | AA8: 0
C9: GENERAL EXPENSES | D9: 5899 | E9: Net Expenses - FSO Only | F9: 0 | G9: 0 | H9: 0 | I9: 0 | J9: 0 | L9: 7690 | M9: Scientific Equipment | N9: 45380 | O9: PO | P9: 27375160 | Q9: 01 | R9: View Document | S9: 45380 | T9: 749517 | U9: - | V9: NIKON INSTRUMENTS INC | W9: Purchase Order - Alexander McGhee - Nikon | X9: NIKON INSTRUMENTS INC | Y9: 0 | Z9: 0 | AA9: 300000
C10: CAPITAL | D10: 7690 | E10: Scientific Equipment | F10: 0 | G10: 300000.07 | H10: 300000.07 | I10: 0 | J10: -300000.07 | N10: 45449 | O10: PRNC | P10: 28062536 | Q10: 01 | R10: View Document | S10: 45449 | T10: 749517 | U10: - | V10: NIKON INSTRUMENTS INC | W10: PO: 749517 Vendor: NIKON INSTRUMENTS INC Account: UA 1101935 Amount: 540233.87 Pay Date: 06/19/2024 | X10: NIKON INSTRUMENTS INC | Y10: 0 | Z10: 300000.07 | AA10: -300000
C11: EXPENSES Total | F11: 0 | G11: 300000.07 | H11: 300000.07 | I11: 0 | J11: -300000.07 | L11: 7690 Total | Y11: 0 | Z11: 300000.07 | AA11: 0
B12: GRAND TOTAL | F12: 0 | G12: 0 | H12: 0 | I12: 0 | J12: 0
